{
    "@context": "https://static.toyobunko-lab.jp/taishozo/context.json",
    "@id": "data:T0663-005.json",
    "ex:sat": [
        {
            "@id": "data:T0663-005.json#SAT頭出し用",
            "ex:url": "https://21dzk.l.u-tokyo.ac.jp/SAT2018/T0663_.16.0335a01.html"
        }
    ],
    "ex:勘同目録": [
        {
            "@id": "data:T0663-005.json#勘同目録",
            "ex:texts": [
                {
                    "@id": "data:T0663-005-1.json#テキスト",
                    "ex:刊写形態": [
                        "写"
                    ],
                    "ex:国": [
                        "日本"
                    ],
                    "ex:年": [
                        "715"
                    ],
                    "ex:時代": [
                        "奈良"
                    ],
                    "ex:標準名称": [
                        "石山寺藏本"
                    ]
                }
            ],
            "ex:❹": [
                "石山寺本"
            ],
            "ex:❼": [
                "石山寺本奈良時代寫"
            ],
            "ex:❼備考": [],
            "ex:底本/校本": [
                "校本"
            ],
            "ex:所蔵者": [
                {
                    "@id": "data:T0663-005-1.json#所蔵者",
                    "ex:国": [
                        "日本"
                    ],
                    "ex:所蔵者": [
                        "石山寺"
                    ]
                }
            ]
        }
    ],
    "ex:勘同目録IIIFコレクション": [
        {
            "@id": "data:T0663.json#勘同目録IIIFコレクション",
            "ex:kmID": [
                "km0664"
            ],
            "ex:toページ": 284,
            "ex:to段": [
                "c"
            ],
            "ex:url": "http://codh.rois.ac.jp/software/iiif-curation-viewer/demo/?manifest=https://static.toyobunko-lab.jp/taishozo/iiif/kandomokuroku/manifest.json&pos=$XXX",
            "ex:ページ": 284,
            "ex:段": [
                "a"
            ]
        }
    ],
    "ex:基本情報": [
        {
            "@id": "data:T0663-005.json#基本情報",
            "ex:No.": "T0663-005",
            "ex:経典": [
                {
                    "@id": "keiten:T0663.json",
                    "ex:出版年月日": 19250515,
                    "ex:収録巻次": 16,
                    "ex:巻数": 4,
                    "ex:枝番": 1,
                    "ex:経典別名": [],
                    "ex:経典名": [
                        "金光明經"
                    ],
                    "ex:経典番号": [
                        "T0663"
                    ],
                    "ex:訳著者": [
                        "北涼曇無讖譯"
                    ],
                    "ex:訳著者1-4": [
                        "曇無讖"
                    ],
                    "ex:部門": [
                        "経集部3"
                    ],
                    "ex:配本": 13
                }
            ]
        }
    ],
    "ex:底本校本URL": [],
    "ex:脚注": [
        {
            "@id": "data:T0663-005.json#脚注",
            "ex:texts": [],
            "ex:所蔵者": []
        }
    ],
    "ex:酉目": [],
    "ex:酉蓮社本IIIコレクション": []
}