{
    "@context": "https://static.toyobunko-lab.jp/taishozo/context.json",
    "@id": "data:T0878_01_002.json",
    "data": {
        "id": "T0878_01_002",
        "relationships": {
            "基本情報 + SAT頭出し用 + 勘同目録IIIFコレクション": {
                "data": {
                    "ID": "T0878_01",
                    "SAT頭出し用：ページ": 335,
                    "SAT頭出し用：枝番+ABC": null,
                    "SAT頭出し用：段": "c",
                    "SAT頭出し用：画像URL": "https://dzkimgs.l.u-tokyo.ac.jp/yurenja_kkz/?manifest=https://dzkimgs.l.u-tokyo.ac.jp/iiif/taisho/manifests/0878_18_manifest.json&canvas=https://dzkimgs.l.u-tokyo.ac.jp/iiif/taisho/manifests/canvas/18_0335.json",
                    "SAT頭出し用：経典番号-ABC": "T0878",
                    "SAT頭出し用：行": 19,
                    "SAT頭出し用：開始巻": 18,
                    "佛經目錄規範資料庫：作訳者1": "不空",
                    "佛經目錄規範資料庫：作訳者2": null,
                    "佛經目錄規範資料庫：作訳者3": null,
                    "佛經目錄規範資料庫：作訳者URL1": "A000095",
                    "佛經目錄規範資料庫：作訳者URL2": null,
                    "佛經目錄規範資料庫：作訳者URL3": null,
                    "佛經目錄規範資料庫：規範碼": "CA0001657",
                    "勘同目録IIIFコレクション：kmID": "km0880",
                    "勘同目録IIIFコレクション：toページ": 311,
                    "勘同目録IIIFコレクション：to段": "a",
                    "勘同目録IIIFコレクション：ページ": 310,
                    "勘同目録IIIFコレクション：段": "c",
                    "勘同目録：❶名称〔巴〕": null,
                    "勘同目録：❶名称〔支〕": "Kin-kang-ting-king-kin-kang-kiai-ta-tao-tch’ang-p’i-lou-tchö-na-jou-lai-tseu-cheou-yong-chen-nei-tcheng-tche-kiuan-chou-fa-chen-yi-ming-fo-tsouei-cheng-tch’eng-pi-mi-sam-mo-ti-li-tsan-wen",
                    "勘同目録：❶名称〔日〕": "Kon-gō-chō-kyō-kon-gō-kai-dai-dō-jō-bi-ru-sha-na-nyo-rai-ji-ju-yū-shin-nai-shō-chi-ken-zoku-hos-shin-i-myō-butsu-sai-jō-jō-hi-mitsu-sam-ma-ji-rai-sam-mon",
                    "勘同目録：❶名称〔梵〕": null,
                    "勘同目録：❶名称〔西藏名〕": null,
                    "勘同目録：❶名称：異名略名": "金剛界大道場毘盧遮那如來自受用身内證智眷屬法身異名佛最上乘祕密三摩地禮懺文金剛頂瑜伽三十七尊禮三十七尊禮懺文",
                    "勘同目録：❷著訳者名、著訳年代": "唐（天寶五－大寶九 A.D. 746-774）不空譯",
                    "勘同目録：❸Nj": 1453,
                    "勘同目録：❸元": "衡",
                    "勘同目録：❸卍": "二十七．二",
                    "勘同目録：❸宋": "衡",
                    "勘同目録：❸明": "隷",
                    "勘同目録：❸縮": "閏十五",
                    "勘同目録：❸麗": "宅",
                    "勘同目録：巻数": 1,
                    "勘同目録：巻数注記": null,
                    "勘同目録：書名": "金剛頂經金剛界大道場毘盧遮那如來自受用身内證智眷屬法身異名佛最上乘祕密三摩地禮懺文",
                    "基本情報：出版年月日": 19280415,
                    "基本情報：収録巻次": 18,
                    "基本情報：巻数": 1,
                    "基本情報：枝番": 1,
                    "基本情報：経典別名": "三十七尊禮懺文,金剛頂瑜伽三十七尊禮",
                    "基本情報：経典名": "金剛頂經金剛界大道場毘盧遮那如來自受用身内證智眷屬法身異名佛最上乘祕密三摩地禮懺文",
                    "基本情報：経典番号": "T0878",
                    "基本情報：訳著者": "唐釋不空譯",
                    "基本情報：訳著者1-4": "釋不空",
                    "基本情報：部門": "密教部1",
                    "基本情報：配本": 48
                }
            }
        },
        "type": "item"
    },
    "ex:sat": [
        {
            "@id": "data:T0878_01_002.json#SAT頭出し用",
            "ex:url": "https://21dzk.l.u-tokyo.ac.jp/SAT2018/T0878_01_.18.0335c19.html"
        }
    ],
    "ex:勘同目録": [
        {
            "@id": "data:T0878_01_002.json#勘同目録",
            "ex:texts": [
                {
                    "@id": "data:T0878_01_002-1.json#テキスト",
                    "ex:刊写形態": "写",
                    "ex:刊写者": "None",
                    "ex:国": "中国",
                    "ex:巻": "None",
                    "ex:年": "805",
                    "ex:時代": "唐",
                    "ex:標準名称": "仁和寺藏三十帖策子本",
                    "ex:関与形態": "None",
                    "ex:関与者": "None"
                }
            ],
            "ex:❹": "三十帖策子本",
            "ex:❼": "None",
            "ex:❼備考": "None",
            "ex:底本/校本": "校本",
            "ex:所蔵者": [
                {
                    "@id": "data:T0878_01_002-1.json#所蔵者",
                    "ex:国": "日本",
                    "ex:所蔵者": "仁和寺"
                }
            ]
        }
    ],
    "ex:勘同目録IIIFコレクション": [
        {
            "@id": "data:T0878_01.json#勘同目録IIIFコレクション",
            "ex:kmID": "km0880",
            "ex:pos": [
                158
            ],
            "ex:toページ": "311",
            "ex:to段": "a",
            "ex:url": [
                "https://static.toyobunko-lab.jp/taishozo/api/iiif/kandomokuroku/manifest.json"
            ],
            "ex:ページ": "310",
            "ex:段": "c"
        }
    ],
    "ex:基本情報": [
        {
            "@id": "data:T0878_01_002.json#基本情報",
            "ex:No.": "T0878_01_002",
            "ex:経典": [
                {
                    "@id": "keiten:T0878_01.json",
                    "ex:出版年月日": "19280415",
                    "ex:収録巻次": "18",
                    "ex:巻数": "1",
                    "ex:枝番": "1",
                    "ex:経典別名": "三十七尊禮懺文,金剛頂瑜伽三十七尊禮",
                    "ex:経典名": "金剛頂經金剛界大道場毘盧遮那如來自受用身内證智眷屬法身異名佛最上乘祕密三摩地禮懺文",
                    "ex:経典番号": "T0878",
                    "ex:訳著者": "唐釋不空譯",
                    "ex:訳著者1-4": "釋不空",
                    "ex:部門": "密教部1",
                    "ex:配本": "48"
                }
            ]
        }
    ],
    "ex:底本校本URL": [],
    "ex:脚注": [
        {
            "@id": "data:T0878_01_002.json#脚注",
            "ex:texts": [
                {
                    "@id": "data:T0878_01_002-1.json#テキスト",
                    "ex:刊写形態": "写",
                    "ex:刊写者": "None",
                    "ex:国": "中国",
                    "ex:巻": "None",
                    "ex:年": "C. 800",
                    "ex:底本推定": "None",
                    "ex:時代": "唐",
                    "ex:標準名称": "仁和寺藏三十帖策子本（第20帖）",
                    "ex:略号の使用": "None",
                    "ex:略号解説": "None",
                    "ex:関与形態": "None",
                    "ex:関与者": "None",
                    "ex:～年": "None"
                }
            ],
            "ex:テキスト": "三十帖策子第二十",
            "ex:備考": "None",
            "ex:底本/校本": "校本",
            "ex:所蔵者": [
                {
                    "@id": "data:T0878_01_002-1.json#所蔵者",
                    "ex:国": "日本",
                    "ex:所蔵者": "仁和寺"
                }
            ],
            "ex:新添": "〈甲〉"
        }
    ],
    "ex:酉目": [],
    "ex:酉蓮社本IIIコレクション": []
}