{
    "@context": "https://static.toyobunko-lab.jp/taishozo/context.json",
    "@id": "data:T1475-006.json",
    "ex:sat": [
        {
            "@id": "data:T1475-006.json#SAT頭出し用",
            "ex:url": "https://21dzk.l.u-tokyo.ac.jp/SAT2018/T1475_.24.0938b12.html"
        }
    ],
    "ex:勘同目録": [
        {
            "@id": "data:T1475-006.json#勘同目録",
            "ex:texts": [
                {
                    "@id": "data:T1475-006-1.json#テキスト",
                    "ex:刊写形態": [
                        "写"
                    ],
                    "ex:国": [
                        "日本"
                    ],
                    "ex:年": [
                        "767"
                    ],
                    "ex:時代": [
                        "奈良"
                    ],
                    "ex:標準名称": [
                        "聖本"
                    ]
                }
            ],
            "ex:❹": [
                "聖本"
            ],
            "ex:❼": [
                "聖語藏景雲經第一六六號・全一卷神護景雲年寫孝謙天皇御願"
            ],
            "ex:❼備考": [],
            "ex:底本/校本": [
                "校本"
            ],
            "ex:所蔵者": [
                {
                    "@id": "data:T1475-006-1.json#所蔵者",
                    "ex:国": [
                        "日本"
                    ],
                    "ex:所蔵者": [
                        "正倉院聖語藏"
                    ]
                }
            ]
        }
    ],
    "ex:勘同目録IIIFコレクション": [
        {
            "@id": "data:T1475.json#勘同目録IIIFコレクション",
            "ex:kmID": [
                "km1506"
            ],
            "ex:pos": [
                250
            ],
            "ex:toページ": [
                402
            ],
            "ex:to段": [
                "a"
            ],
            "ex:url": [
                "https://static.toyobunko-lab.jp/taishozo/api/iiif/kandomokuroku/manifest.json"
            ],
            "ex:ページ": [
                401
            ],
            "ex:段": [
                "c"
            ]
        }
    ],
    "ex:基本情報": [
        {
            "@id": "data:T1475-006.json#基本情報",
            "ex:No.": "T1475-006",
            "ex:経典": [
                {
                    "@id": "keiten:T1475.json",
                    "ex:出版年月日": [
                        19260615
                    ],
                    "ex:収録巻次": [
                        24
                    ],
                    "ex:巻数": [
                        1
                    ],
                    "ex:枝番": [
                        1
                    ],
                    "ex:経典別名": [
                        "沙彌尼戒文"
                    ],
                    "ex:経典名": [
                        "沙彌尼離戒文"
                    ],
                    "ex:経典番号": [
                        "T1475"
                    ],
                    "ex:訳著者": [
                        "東晉闕名譯"
                    ],
                    "ex:訳著者1-4": [],
                    "ex:部門": [
                        "律部3"
                    ],
                    "ex:配本": [
                        26
                    ]
                }
            ]
        }
    ],
    "ex:底本校本URL": [],
    "ex:脚注": [
        {
            "@id": "data:T1475-006.json#脚注",
            "ex:texts": [
                {
                    "@id": "data:T1475-006-1.json#テキスト",
                    "ex:刊写形態": [
                        "写"
                    ],
                    "ex:刊写者": [],
                    "ex:国": [],
                    "ex:巻": [],
                    "ex:年": [],
                    "ex:底本推定": [],
                    "ex:時代": [],
                    "ex:標準名称": [
                        "聖本"
                    ],
                    "ex:略号の使用": [
                        "専号使用"
                    ],
                    "ex:略号解説": [
                        "〈聖〉正倉院聖語藏本（天平寫經）（The Tempyō Mss.〔A. D. 729-〕and the Chinese Mss. of the Sui〔A. D. 581-617〕 and Tang〔A. D. 618-822〕dynasties, belonging to the Imperial Treasure House Shōsō-in at Nara, specially called Shōgo-zō）"
                    ],
                    "ex:関与形態": [],
                    "ex:関与者": [],
                    "ex:～年": []
                }
            ],
            "ex:テキスト": [
                "〈聖〉"
            ],
            "ex:備考": [],
            "ex:底本/校本": [
                "校本"
            ],
            "ex:所蔵者": [
                {
                    "@id": "data:T1475-006-1.json#所蔵者",
                    "ex:国": [
                        "日本"
                    ],
                    "ex:所蔵者": [
                        "正倉院聖語藏"
                    ]
                }
            ],
            "ex:新添": []
        }
    ],
    "ex:酉目": [],
    "ex:酉蓮社本IIIコレクション": []
}