{
    "@context": "https://static.toyobunko-lab.jp/taishozo/context.json",
    "@id": "data:T1545_01_005.json",
    "data": {
        "id": "T1545_01_005",
        "relationships": {
            "基本情報 + SAT頭出し用 + 勘同目録IIIFコレクション": {
                "data": {
                    "ID": "T1545_01",
                    "SAT頭出し用：ページ": 1,
                    "SAT頭出し用：枝番+ABC": null,
                    "SAT頭出し用：段": "a",
                    "SAT頭出し用：画像URL": "https://dzkimgs.l.u-tokyo.ac.jp/yurenja_kkz/?manifest=https://dzkimgs.l.u-tokyo.ac.jp/iiif/taisho/manifests/1545_27_manifest.json&canvas=https://dzkimgs.l.u-tokyo.ac.jp/iiif/taisho/manifests/canvas/27_0001.json",
                    "SAT頭出し用：経典番号-ABC": "T1545",
                    "SAT頭出し用：行": 1,
                    "SAT頭出し用：開始巻": 27,
                    "佛經目錄規範資料庫：作訳者1": "玄奘",
                    "佛經目錄規範資料庫：作訳者2": null,
                    "佛經目錄規範資料庫：作訳者3": null,
                    "佛經目錄規範資料庫：作訳者URL1": "A000294",
                    "佛經目錄規範資料庫：作訳者URL2": null,
                    "佛經目錄規範資料庫：作訳者URL3": null,
                    "佛經目錄規範資料庫：規範碼": "CA0000051",
                    "勘同目録IIIFコレクション：kmID": "km1576",
                    "勘同目録IIIFコレクション：toページ": 415,
                    "勘同目録IIIFコレクション：to段": "c",
                    "勘同目録IIIFコレクション：ページ": 415,
                    "勘同目録IIIFコレクション：段": "a",
                    "勘同目録：❶名称〔巴〕": null,
                    "勘同目録：❶名称〔支〕": "A-p’i-ta-mo-ta-p’i-p’o-cha-louen",
                    "勘同目録：❶名称〔日〕": "A-bi-datsu-ma-dai-bi-ba-sha-ron",
                    "勘同目録：❶名称〔梵〕": "Abhidharmamahā-vibhāṣā-śāstra",
                    "勘同目録：❶名称〔西藏名〕": null,
                    "勘同目録：❶名称：異名略名": "大毘婆沙論,大毘婆沙,婆沙",
                    "勘同目録：❷著訳者名、著訳年代": "唐（顯慶元－四 A.D. 656-659） 玄奘譯",
                    "勘同目録：❸Nj": 1263,
                    "勘同目録：❸元": "惻至神",
                    "勘同目録：❸卍": "二十二．六－二十三．三",
                    "勘同目録：❸宋": "惻至神",
                    "勘同目録：❸明": "心至縻",
                    "勘同目録：❸縮": "收一－八",
                    "勘同目録：❸麗": "仁至逸",
                    "勘同目録：巻数": 200,
                    "勘同目録：巻数注記": null,
                    "勘同目録：書名": "阿毘達磨大毘婆沙論",
                    "基本情報：出版年月日": 19260715,
                    "基本情報：収録巻次": 27,
                    "基本情報：巻数": 200,
                    "基本情報：枝番": 1,
                    "基本情報：経典別名": "説一切有部發智大毘婆沙論,大毘婆沙論,婆沙論",
                    "基本情報：経典名": "阿毘達磨大毘婆沙論",
                    "基本情報：経典番号": "T1545",
                    "基本情報：訳著者": "五百大阿羅漢等造　唐釋玄奘譯",
                    "基本情報：訳著者1-4": "五百大阿羅漢|釋玄奘",
                    "基本情報：部門": "毘曇部2",
                    "基本情報：配本": 27
                }
            }
        },
        "type": "item"
    },
    "ex:sat": [
        {
            "@id": "data:T1545_01_005.json#SAT頭出し用",
            "ex:url": "https://21dzk.l.u-tokyo.ac.jp/SAT2018/T1545_01_.27.0001a01.html"
        }
    ],
    "ex:勘同目録": [
        {
            "@id": "data:T1545_01_005.json#勘同目録",
            "ex:texts": [
                {
                    "@id": "data:T1545_01_005-1.json#テキスト",
                    "ex:刊写形態": "刊",
                    "ex:刊写者": "None",
                    "ex:国": "中国",
                    "ex:巻": "None",
                    "ex:年": "1104",
                    "ex:時代": "宋",
                    "ex:標準名称": "宮本",
                    "ex:関与形態": "None",
                    "ex:関与者": "None"
                }
            ],
            "ex:❹": "宮本",
            "ex:❼": "None",
            "ex:❼備考": "None",
            "ex:底本/校本": "校本",
            "ex:所蔵者": [
                {
                    "@id": "data:T1545_01_005-1.json#所蔵者",
                    "ex:国": "日本",
                    "ex:所蔵者": "宮内庁書陵部"
                }
            ]
        }
    ],
    "ex:勘同目録IIIFコレクション": [
        {
            "@id": "data:T1545_01.json#勘同目録IIIFコレクション",
            "ex:kmID": "km1576",
            "ex:pos": [
                263
            ],
            "ex:toページ": "415",
            "ex:to段": "c",
            "ex:url": [
                "https://static.toyobunko-lab.jp/taishozo/api/iiif/kandomokuroku/manifest.json"
            ],
            "ex:ページ": "415",
            "ex:段": "a"
        }
    ],
    "ex:基本情報": [
        {
            "@id": "data:T1545_01_005.json#基本情報",
            "ex:No.": "T1545_01_005",
            "ex:経典": [
                {
                    "@id": "keiten:T1545_01.json",
                    "ex:出版年月日": "19260715",
                    "ex:収録巻次": "27",
                    "ex:巻数": "200",
                    "ex:枝番": "1",
                    "ex:経典別名": "説一切有部發智大毘婆沙論,大毘婆沙論,婆沙論",
                    "ex:経典名": "阿毘達磨大毘婆沙論",
                    "ex:経典番号": "T1545",
                    "ex:訳著者": "五百大阿羅漢等造　唐釋玄奘譯",
                    "ex:訳著者1-4": "五百大阿羅漢|釋玄奘",
                    "ex:部門": "毘曇部2",
                    "ex:配本": "27"
                }
            ]
        }
    ],
    "ex:底本校本URL": [
        {
            "@id": "data:T1545_01_005-001.json#底本・校本URL",
            "ex:TEIURL": "None",
            "ex:書誌URL": "https://db2.sido.keio.ac.jp/kanseki/bib_detail?bibid=007075_0968",
            "ex:画像URL": "https://db2.sido.keio.ac.jp/kanseki/bib_frame?id=007075-4004&page=2",
            "ex:經典名稱": [
                "阿 (唐)"
            ],
            "ex:資料群名": "宮内庁書陵部蔵宋版大蔵経"
        },
        {
            "@id": "data:T1545_01_005-002.json#底本・校本URL",
            "ex:TEIURL": "None",
            "ex:書誌URL": "https://db2.sido.keio.ac.jp/kanseki/bib_detail?bibid=007075_0968",
            "ex:画像URL": "https://db2.sido.keio.ac.jp/kanseki/bib_frame?id=007075-4004&page=5",
            "ex:經典名稱": [
                "阿 (唐)"
            ],
            "ex:資料群名": "宮内庁書陵部蔵宋版大蔵経"
        },
        {
            "@id": "data:T1545_01_005-003.json#底本・校本URL",
            "ex:TEIURL": "None",
            "ex:書誌URL": "https://db2.sido.keio.ac.jp/kanseki/bib_detail?bibid=007075_0968",
            "ex:画像URL": "https://db2.sido.keio.ac.jp/kanseki/bib_frame?id=007075-4004&page=6",
            "ex:經典名稱": [
                "阿 (卷)"
            ],
            "ex:資料群名": "宮内庁書陵部蔵宋版大蔵経"
        },
        {
            "@id": "data:T1545_01_005-004.json#底本・校本URL",
            "ex:TEIURL": "None",
            "ex:書誌URL": "https://db2.sido.keio.ac.jp/kanseki/bib_detail?bibid=007075_0968",
            "ex:画像URL": "https://db2.sido.keio.ac.jp/kanseki/bib_frame?id=007075-4005&page=2",
            "ex:經典名稱": [
                "阿 (卷)"
            ],
            "ex:資料群名": "宮内庁書陵部蔵宋版大蔵経"
        },
        {
            "@id": "data:T1545_01_005-005.json#底本・校本URL",
            "ex:TEIURL": "None",
            "ex:書誌URL": "https://db2.sido.keio.ac.jp/kanseki/bib_detail?bibid=007075_0968",
            "ex:画像URL": "https://db2.sido.keio.ac.jp/kanseki/bib_frame?id=007075-4006&page=3",
            "ex:經典名稱": [
                "阿 (卷)"
            ],
            "ex:資料群名": "宮内庁書陵部蔵宋版大蔵経"
        },
        {
            "@id": "data:T1545_01_005-006.json#底本・校本URL",
            "ex:TEIURL": "None",
            "ex:書誌URL": "https://db2.sido.keio.ac.jp/kanseki/bib_detail?bibid=007075_0968",
            "ex:画像URL": "https://db2.sido.keio.ac.jp/kanseki/bib_frame?id=007075-4007&page=2",
            "ex:經典名稱": [
                "阿 (卷)"
            ],
            "ex:資料群名": "宮内庁書陵部蔵宋版大蔵経"
        },
        {
            "@id": "data:T1545_01_005-007.json#底本・校本URL",
            "ex:TEIURL": "None",
            "ex:書誌URL": "https://db2.sido.keio.ac.jp/kanseki/bib_detail?bibid=007075_0968",
            "ex:画像URL": "https://db2.sido.keio.ac.jp/kanseki/bib_frame?id=007075-4008&page=3",
            "ex:經典名稱": [
                "阿 (卷)"
            ],
            "ex:資料群名": "宮内庁書陵部蔵宋版大蔵経"
        },
        {
            "@id": "data:T1545_01_005-008.json#底本・校本URL",
            "ex:TEIURL": "None",
            "ex:書誌URL": "https://db2.sido.keio.ac.jp/kanseki/bib_detail?bibid=007075_0968",
            "ex:画像URL": "https://db2.sido.keio.ac.jp/kanseki/bib_frame?id=007075-4009&page=2",
            "ex:經典名稱": [
                "阿 (卷)"
            ],
            "ex:資料群名": "宮内庁書陵部蔵宋版大蔵経"
        },
        {
            "@id": "data:T1545_01_005-009.json#底本・校本URL",
            "ex:TEIURL": "None",
            "ex:書誌URL": "https://db2.sido.keio.ac.jp/kanseki/bib_detail?bibid=007075_0968",
            "ex:画像URL": "https://db2.sido.keio.ac.jp/kanseki/bib_frame?id=007075-4010&page=2",
            "ex:經典名稱": [
                "阿 (卷)"
            ],
            "ex:資料群名": "宮内庁書陵部蔵宋版大蔵経"
        },
        {
            "@id": "data:T1545_01_005-010.json#底本・校本URL",
            "ex:TEIURL": "None",
            "ex:書誌URL": "https://db2.sido.keio.ac.jp/kanseki/bib_detail?bibid=007075_0968",
            "ex:画像URL": "https://db2.sido.keio.ac.jp/kanseki/bib_frame?id=007075-4011&page=2",
            "ex:經典名稱": [
                "阿 (卷)"
            ],
            "ex:資料群名": "宮内庁書陵部蔵宋版大蔵経"
        },
        {
            "@id": "data:T1545_01_005-011.json#底本・校本URL",
            "ex:TEIURL": "None",
            "ex:書誌URL": "https://db2.sido.keio.ac.jp/kanseki/bib_detail?bibid=007075_0968",
            "ex:画像URL": "https://db2.sido.keio.ac.jp/kanseki/bib_frame?id=007075-4012&page=2",
            "ex:經典名稱": [
                "阿 (卷)"
            ],
            "ex:資料群名": "宮内庁書陵部蔵宋版大蔵経"
        },
        {
            "@id": "data:T1545_01_005-012.json#底本・校本URL",
            "ex:TEIURL": "None",
            "ex:書誌URL": "https://db2.sido.keio.ac.jp/kanseki/bib_detail?bibid=007075_0968",
            "ex:画像URL": "https://db2.sido.keio.ac.jp/kanseki/bib_frame?id=007075-4013&page=2",
            "ex:經典名稱": [
                "阿 (卷)"
            ],
            "ex:資料群名": "宮内庁書陵部蔵宋版大蔵経"
        },
        {
            "@id": "data:T1545_01_005-013.json#底本・校本URL",
            "ex:TEIURL": "None",
            "ex:書誌URL": "https://db2.sido.keio.ac.jp/kanseki/bib_detail?bibid=007075_0968",
            "ex:画像URL": "https://db2.sido.keio.ac.jp/kanseki/bib_frame?id=007075-4015&page=2",
            "ex:經典名稱": [
                "阿 (卷)"
            ],
            "ex:資料群名": "宮内庁書陵部蔵宋版大蔵経"
        },
        {
            "@id": "data:T1545_01_005-014.json#底本・校本URL",
            "ex:TEIURL": "None",
            "ex:書誌URL": "https://db2.sido.keio.ac.jp/kanseki/bib_detail?bibid=007075_0968",
            "ex:画像URL": "https://db2.sido.keio.ac.jp/kanseki/bib_frame?id=007075-4016&page=2",
            "ex:經典名稱": [
                "阿 (卷)"
            ],
            "ex:資料群名": "宮内庁書陵部蔵宋版大蔵経"
        },
        {
            "@id": "data:T1545_01_005-015.json#底本・校本URL",
            "ex:TEIURL": "None",
            "ex:書誌URL": "https://db2.sido.keio.ac.jp/kanseki/bib_detail?bibid=007075_0968",
            "ex:画像URL": "https://db2.sido.keio.ac.jp/kanseki/bib_frame?id=007075-4017&page=2",
            "ex:經典名稱": [
                "阿 (卷)"
            ],
            "ex:資料群名": "宮内庁書陵部蔵宋版大蔵経"
        },
        {
            "@id": "data:T1545_01_005-016.json#底本・校本URL",
            "ex:TEIURL": "None",
            "ex:書誌URL": "https://db2.sido.keio.ac.jp/kanseki/bib_detail?bibid=007075_0968",
            "ex:画像URL": "https://db2.sido.keio.ac.jp/kanseki/bib_frame?id=007075-4018&page=3",
            "ex:經典名稱": [
                "阿 (卷)"
            ],
            "ex:資料群名": "宮内庁書陵部蔵宋版大蔵経"
        },
        {
            "@id": "data:T1545_01_005-017.json#底本・校本URL",
            "ex:TEIURL": "None",
            "ex:書誌URL": "https://db2.sido.keio.ac.jp/kanseki/bib_detail?bibid=007075_0968",
            "ex:画像URL": "https://db2.sido.keio.ac.jp/kanseki/bib_frame?id=007075-4019&page=3",
            "ex:經典名稱": [
                "阿 (卷)"
            ],
            "ex:資料群名": "宮内庁書陵部蔵宋版大蔵経"
        },
        {
            "@id": "data:T1545_01_005-018.json#底本・校本URL",
            "ex:TEIURL": "None",
            "ex:書誌URL": "https://db2.sido.keio.ac.jp/kanseki/bib_detail?bibid=007075_0968",
            "ex:画像URL": "https://db2.sido.keio.ac.jp/kanseki/bib_frame?id=007075-4020&page=3",
            "ex:經典名稱": [
                "阿 (卷)"
            ],
            "ex:資料群名": "宮内庁書陵部蔵宋版大蔵経"
        },
        {
            "@id": "data:T1545_01_005-019.json#底本・校本URL",
            "ex:TEIURL": "None",
            "ex:書誌URL": "https://db2.sido.keio.ac.jp/kanseki/bib_detail?bibid=007075_0968",
            "ex:画像URL": "https://db2.sido.keio.ac.jp/kanseki/bib_frame?id=007075-4021&page=3",
            "ex:經典名稱": [
                "阿 (卷)"
            ],
            "ex:資料群名": "宮内庁書陵部蔵宋版大蔵経"
        },
        {
            "@id": "data:T1545_01_005-020.json#底本・校本URL",
            "ex:TEIURL": "None",
            "ex:書誌URL": "https://db2.sido.keio.ac.jp/kanseki/bib_detail?bibid=007075_0968",
            "ex:画像URL": "https://db2.sido.keio.ac.jp/kanseki/bib_frame?id=007075-4022&page=2",
            "ex:經典名稱": [
                "阿 (卷)"
            ],
            "ex:資料群名": "宮内庁書陵部蔵宋版大蔵経"
        },
        {
            "@id": "data:T1545_01_005-021.json#底本・校本URL",
            "ex:TEIURL": "None",
            "ex:書誌URL": "https://db2.sido.keio.ac.jp/kanseki/bib_detail?bibid=007075_0968",
            "ex:画像URL": "https://db2.sido.keio.ac.jp/kanseki/bib_frame?id=007075-4023&page=2",
            "ex:經典名稱": [
                "阿 (卷)"
            ],
            "ex:資料群名": "宮内庁書陵部蔵宋版大蔵経"
        },
        {
            "@id": "data:T1545_01_005-022.json#底本・校本URL",
            "ex:TEIURL": "None",
            "ex:書誌URL": "https://db2.sido.keio.ac.jp/kanseki/bib_detail?bibid=007075_0968",
            "ex:画像URL": "https://db2.sido.keio.ac.jp/kanseki/bib_frame?id=007075-4024&page=2",
            "ex:經典名稱": [
                "阿 (卷)"
            ],
            "ex:資料群名": "宮内庁書陵部蔵宋版大蔵経"
        },
        {
            "@id": "data:T1545_01_005-023.json#底本・校本URL",
            "ex:TEIURL": "None",
            "ex:書誌URL": "https://db2.sido.keio.ac.jp/kanseki/bib_detail?bibid=007075_0968",
            "ex:画像URL": "https://db2.sido.keio.ac.jp/kanseki/bib_frame?id=007075-4026&page=3",
            "ex:經典名稱": [
                "阿 (卷)"
            ],
            "ex:資料群名": "宮内庁書陵部蔵宋版大蔵経"
        },
        {
            "@id": "data:T1545_01_005-024.json#底本・校本URL",
            "ex:TEIURL": "None",
            "ex:書誌URL": "https://db2.sido.keio.ac.jp/kanseki/bib_detail?bibid=007075_0968",
            "ex:画像URL": "https://db2.sido.keio.ac.jp/kanseki/bib_frame?id=007075-4027&page=3",
            "ex:經典名稱": [
                "阿 (卷)"
            ],
            "ex:資料群名": "宮内庁書陵部蔵宋版大蔵経"
        },
        {
            "@id": "data:T1545_01_005-025.json#底本・校本URL",
            "ex:TEIURL": "None",
            "ex:書誌URL": "https://db2.sido.keio.ac.jp/kanseki/bib_detail?bibid=007075_0968",
            "ex:画像URL": "https://db2.sido.keio.ac.jp/kanseki/bib_frame?id=007075-4028&page=3",
            "ex:經典名稱": [
                "阿 (卷)"
            ],
            "ex:資料群名": "宮内庁書陵部蔵宋版大蔵経"
        },
        {
            "@id": "data:T1545_01_005-026.json#底本・校本URL",
            "ex:TEIURL": "None",
            "ex:書誌URL": "https://db2.sido.keio.ac.jp/kanseki/bib_detail?bibid=007075_0968",
            "ex:画像URL": "https://db2.sido.keio.ac.jp/kanseki/bib_frame?id=007075-4029&page=3",
            "ex:經典名稱": [
                "阿 (卷)"
            ],
            "ex:資料群名": "宮内庁書陵部蔵宋版大蔵経"
        },
        {
            "@id": "data:T1545_01_005-027.json#底本・校本URL",
            "ex:TEIURL": "None",
            "ex:書誌URL": "https://db2.sido.keio.ac.jp/kanseki/bib_detail?bibid=007075_0968",
            "ex:画像URL": "https://db2.sido.keio.ac.jp/kanseki/bib_frame?id=007075-4030&page=2",
            "ex:經典名稱": [
                "阿 (卷)"
            ],
            "ex:資料群名": "宮内庁書陵部蔵宋版大蔵経"
        },
        {
            "@id": "data:T1545_01_005-028.json#底本・校本URL",
            "ex:TEIURL": "None",
            "ex:書誌URL": "https://db2.sido.keio.ac.jp/kanseki/bib_detail?bibid=007075_0968",
            "ex:画像URL": "https://db2.sido.keio.ac.jp/kanseki/bib_frame?id=007075-4031&page=3",
            "ex:經典名稱": [
                "阿 (卷)"
            ],
            "ex:資料群名": "宮内庁書陵部蔵宋版大蔵経"
        },
        {
            "@id": "data:T1545_01_005-029.json#底本・校本URL",
            "ex:TEIURL": "None",
            "ex:書誌URL": "https://db2.sido.keio.ac.jp/kanseki/bib_detail?bibid=007075_0968",
            "ex:画像URL": "https://db2.sido.keio.ac.jp/kanseki/bib_frame?id=007075-4032&page=3",
            "ex:經典名稱": [
                "阿 (卷)"
            ],
            "ex:資料群名": "宮内庁書陵部蔵宋版大蔵経"
        },
        {
            "@id": "data:T1545_01_005-030.json#底本・校本URL",
            "ex:TEIURL": "None",
            "ex:書誌URL": "https://db2.sido.keio.ac.jp/kanseki/bib_detail?bibid=007075_0968",
            "ex:画像URL": "https://db2.sido.keio.ac.jp/kanseki/bib_frame?id=007075-4033&page=2",
            "ex:經典名稱": [
                "阿 (卷)"
            ],
            "ex:資料群名": "宮内庁書陵部蔵宋版大蔵経"
        },
        {
            "@id": "data:T1545_01_005-031.json#底本・校本URL",
            "ex:TEIURL": "None",
            "ex:書誌URL": "https://db2.sido.keio.ac.jp/kanseki/bib_detail?bibid=007075_0968",
            "ex:画像URL": "https://db2.sido.keio.ac.jp/kanseki/bib_frame?id=007075-4034&page=3",
            "ex:經典名稱": [
                "阿 (卷)"
            ],
            "ex:資料群名": "宮内庁書陵部蔵宋版大蔵経"
        },
        {
            "@id": "data:T1545_01_005-032.json#底本・校本URL",
            "ex:TEIURL": "None",
            "ex:書誌URL": "https://db2.sido.keio.ac.jp/kanseki/bib_detail?bibid=007075_0968",
            "ex:画像URL": "https://db2.sido.keio.ac.jp/kanseki/bib_frame?id=007075-4035&page=2",
            "ex:經典名稱": [
                "阿 (卷)"
            ],
            "ex:資料群名": "宮内庁書陵部蔵宋版大蔵経"
        },
        {
            "@id": "data:T1545_01_005-033.json#底本・校本URL",
            "ex:TEIURL": "None",
            "ex:書誌URL": "https://db2.sido.keio.ac.jp/kanseki/bib_detail?bibid=007075_0968",
            "ex:画像URL": "https://db2.sido.keio.ac.jp/kanseki/bib_frame?id=007075-4037&page=2",
            "ex:經典名稱": [
                "阿 (卷)"
            ],
            "ex:資料群名": "宮内庁書陵部蔵宋版大蔵経"
        },
        {
            "@id": "data:T1545_01_005-034.json#底本・校本URL",
            "ex:TEIURL": "None",
            "ex:書誌URL": "https://db2.sido.keio.ac.jp/kanseki/bib_detail?bibid=007075_0968",
            "ex:画像URL": "https://db2.sido.keio.ac.jp/kanseki/bib_frame?id=007075-4038&page=2",
            "ex:經典名稱": [
                "阿 (卷)"
            ],
            "ex:資料群名": "宮内庁書陵部蔵宋版大蔵経"
        },
        {
            "@id": "data:T1545_01_005-035.json#底本・校本URL",
            "ex:TEIURL": "None",
            "ex:書誌URL": "https://db2.sido.keio.ac.jp/kanseki/bib_detail?bibid=007075_0968",
            "ex:画像URL": "https://db2.sido.keio.ac.jp/kanseki/bib_frame?id=007075-4039&page=2",
            "ex:經典名稱": [
                "阿 (卷)"
            ],
            "ex:資料群名": "宮内庁書陵部蔵宋版大蔵経"
        },
        {
            "@id": "data:T1545_01_005-036.json#底本・校本URL",
            "ex:TEIURL": "None",
            "ex:書誌URL": "https://db2.sido.keio.ac.jp/kanseki/bib_detail?bibid=007075_0968",
            "ex:画像URL": "https://db2.sido.keio.ac.jp/kanseki/bib_frame?id=007075-4040&page=3",
            "ex:經典名稱": [
                "阿 (卷)"
            ],
            "ex:資料群名": "宮内庁書陵部蔵宋版大蔵経"
        },
        {
            "@id": "data:T1545_01_005-037.json#底本・校本URL",
            "ex:TEIURL": "None",
            "ex:書誌URL": "https://db2.sido.keio.ac.jp/kanseki/bib_detail?bibid=007075_0968",
            "ex:画像URL": "https://db2.sido.keio.ac.jp/kanseki/bib_frame?id=007075-4041&page=3",
            "ex:經典名稱": [
                "阿 (卷)"
            ],
            "ex:資料群名": "宮内庁書陵部蔵宋版大蔵経"
        },
        {
            "@id": "data:T1545_01_005-038.json#底本・校本URL",
            "ex:TEIURL": "None",
            "ex:書誌URL": "https://db2.sido.keio.ac.jp/kanseki/bib_detail?bibid=007075_0968",
            "ex:画像URL": "https://db2.sido.keio.ac.jp/kanseki/bib_frame?id=007075-4042&page=3",
            "ex:經典名稱": [
                "阿 (卷)"
            ],
            "ex:資料群名": "宮内庁書陵部蔵宋版大蔵経"
        },
        {
            "@id": "data:T1545_01_005-039.json#底本・校本URL",
            "ex:TEIURL": "None",
            "ex:書誌URL": "https://db2.sido.keio.ac.jp/kanseki/bib_detail?bibid=007075_0968",
            "ex:画像URL": "https://db2.sido.keio.ac.jp/kanseki/bib_frame?id=007075-4043&page=3",
            "ex:經典名稱": [
                "阿 (卷)"
            ],
            "ex:資料群名": "宮内庁書陵部蔵宋版大蔵経"
        },
        {
            "@id": "data:T1545_01_005-040.json#底本・校本URL",
            "ex:TEIURL": "None",
            "ex:書誌URL": "https://db2.sido.keio.ac.jp/kanseki/bib_detail?bibid=007075_0968",
            "ex:画像URL": "https://db2.sido.keio.ac.jp/kanseki/bib_frame?id=007075-4044&page=2",
            "ex:經典名稱": [
                "阿 (卷)"
            ],
            "ex:資料群名": "宮内庁書陵部蔵宋版大蔵経"
        },
        {
            "@id": "data:T1545_01_005-041.json#底本・校本URL",
            "ex:TEIURL": "None",
            "ex:書誌URL": "https://db2.sido.keio.ac.jp/kanseki/bib_detail?bibid=007075_0968",
            "ex:画像URL": "https://db2.sido.keio.ac.jp/kanseki/bib_frame?id=007075-4045&page=3",
            "ex:經典名稱": [
                "阿 (卷)"
            ],
            "ex:資料群名": "宮内庁書陵部蔵宋版大蔵経"
        },
        {
            "@id": "data:T1545_01_005-042.json#底本・校本URL",
            "ex:TEIURL": "None",
            "ex:書誌URL": "https://db2.sido.keio.ac.jp/kanseki/bib_detail?bibid=007075_0968",
            "ex:画像URL": "https://db2.sido.keio.ac.jp/kanseki/bib_frame?id=007075-4046&page=2",
            "ex:經典名稱": [
                "阿 (卷)"
            ],
            "ex:資料群名": "宮内庁書陵部蔵宋版大蔵経"
        },
        {
            "@id": "data:T1545_01_005-043.json#底本・校本URL",
            "ex:TEIURL": "None",
            "ex:書誌URL": "https://db2.sido.keio.ac.jp/kanseki/bib_detail?bibid=007075_0968",
            "ex:画像URL": "https://db2.sido.keio.ac.jp/kanseki/bib_frame?id=007075-4048&page=3",
            "ex:經典名稱": [
                "阿 (卷)"
            ],
            "ex:資料群名": "宮内庁書陵部蔵宋版大蔵経"
        },
        {
            "@id": "data:T1545_01_005-044.json#底本・校本URL",
            "ex:TEIURL": "None",
            "ex:書誌URL": "https://db2.sido.keio.ac.jp/kanseki/bib_detail?bibid=007075_0968",
            "ex:画像URL": "https://db2.sido.keio.ac.jp/kanseki/bib_frame?id=007075-4049&page=2",
            "ex:經典名稱": [
                "阿 (卷)"
            ],
            "ex:資料群名": "宮内庁書陵部蔵宋版大蔵経"
        },
        {
            "@id": "data:T1545_01_005-045.json#底本・校本URL",
            "ex:TEIURL": "None",
            "ex:書誌URL": "https://db2.sido.keio.ac.jp/kanseki/bib_detail?bibid=007075_0968",
            "ex:画像URL": "https://db2.sido.keio.ac.jp/kanseki/bib_frame?id=007075-4050&page=3",
            "ex:經典名稱": [
                "阿 (卷)"
            ],
            "ex:資料群名": "宮内庁書陵部蔵宋版大蔵経"
        },
        {
            "@id": "data:T1545_01_005-046.json#底本・校本URL",
            "ex:TEIURL": "None",
            "ex:書誌URL": "https://db2.sido.keio.ac.jp/kanseki/bib_detail?bibid=007075_0968",
            "ex:画像URL": "https://db2.sido.keio.ac.jp/kanseki/bib_frame?id=007075-4051&page=2",
            "ex:經典名稱": [
                "阿 (卷)"
            ],
            "ex:資料群名": "宮内庁書陵部蔵宋版大蔵経"
        },
        {
            "@id": "data:T1545_01_005-047.json#底本・校本URL",
            "ex:TEIURL": "None",
            "ex:書誌URL": "https://db2.sido.keio.ac.jp/kanseki/bib_detail?bibid=007075_0968",
            "ex:画像URL": "https://db2.sido.keio.ac.jp/kanseki/bib_frame?id=007075-4052&page=2",
            "ex:經典名稱": [
                "阿 (卷)"
            ],
            "ex:資料群名": "宮内庁書陵部蔵宋版大蔵経"
        },
        {
            "@id": "data:T1545_01_005-048.json#底本・校本URL",
            "ex:TEIURL": "None",
            "ex:書誌URL": "https://db2.sido.keio.ac.jp/kanseki/bib_detail?bibid=007075_0968",
            "ex:画像URL": "https://db2.sido.keio.ac.jp/kanseki/bib_frame?id=007075-4053&page=2",
            "ex:經典名稱": [
                "阿 (卷)"
            ],
            "ex:資料群名": "宮内庁書陵部蔵宋版大蔵経"
        },
        {
            "@id": "data:T1545_01_005-049.json#底本・校本URL",
            "ex:TEIURL": "None",
            "ex:書誌URL": "https://db2.sido.keio.ac.jp/kanseki/bib_detail?bibid=007075_0968",
            "ex:画像URL": "https://db2.sido.keio.ac.jp/kanseki/bib_frame?id=007075-4054&page=2",
            "ex:經典名稱": [
                "阿 (卷)"
            ],
            "ex:資料群名": "宮内庁書陵部蔵宋版大蔵経"
        },
        {
            "@id": "data:T1545_01_005-050.json#底本・校本URL",
            "ex:TEIURL": "None",
            "ex:書誌URL": "https://db2.sido.keio.ac.jp/kanseki/bib_detail?bibid=007075_0968",
            "ex:画像URL": "https://db2.sido.keio.ac.jp/kanseki/bib_frame?id=007075-4055&page=2",
            "ex:經典名稱": [
                "阿 (卷)"
            ],
            "ex:資料群名": "宮内庁書陵部蔵宋版大蔵経"
        },
        {
            "@id": "data:T1545_01_005-051.json#底本・校本URL",
            "ex:TEIURL": "None",
            "ex:書誌URL": "https://db2.sido.keio.ac.jp/kanseki/bib_detail?bibid=007075_0968",
            "ex:画像URL": "https://db2.sido.keio.ac.jp/kanseki/bib_frame?id=007075-4056&page=2",
            "ex:經典名稱": [
                "阿 (卷)"
            ],
            "ex:資料群名": "宮内庁書陵部蔵宋版大蔵経"
        },
        {
            "@id": "data:T1545_01_005-052.json#底本・校本URL",
            "ex:TEIURL": "None",
            "ex:書誌URL": "https://db2.sido.keio.ac.jp/kanseki/bib_detail?bibid=007075_0968",
            "ex:画像URL": "https://db2.sido.keio.ac.jp/kanseki/bib_frame?id=007075-4057&page=2",
            "ex:經典名稱": [
                "阿 (卷)"
            ],
            "ex:資料群名": "宮内庁書陵部蔵宋版大蔵経"
        },
        {
            "@id": "data:T1545_01_005-053.json#底本・校本URL",
            "ex:TEIURL": "None",
            "ex:書誌URL": "https://db2.sido.keio.ac.jp/kanseki/bib_detail?bibid=007075_0968",
            "ex:画像URL": "https://db2.sido.keio.ac.jp/kanseki/bib_frame?id=007075-4059&page=3",
            "ex:經典名稱": [
                "阿 (卷)"
            ],
            "ex:資料群名": "宮内庁書陵部蔵宋版大蔵経"
        },
        {
            "@id": "data:T1545_01_005-054.json#底本・校本URL",
            "ex:TEIURL": "None",
            "ex:書誌URL": "https://db2.sido.keio.ac.jp/kanseki/bib_detail?bibid=007075_0968",
            "ex:画像URL": "https://db2.sido.keio.ac.jp/kanseki/bib_frame?id=007075-4060&page=3",
            "ex:經典名稱": [
                "阿 (卷)"
            ],
            "ex:資料群名": "宮内庁書陵部蔵宋版大蔵経"
        },
        {
            "@id": "data:T1545_01_005-055.json#底本・校本URL",
            "ex:TEIURL": "None",
            "ex:書誌URL": "https://db2.sido.keio.ac.jp/kanseki/bib_detail?bibid=007075_0968",
            "ex:画像URL": "https://db2.sido.keio.ac.jp/kanseki/bib_frame?id=007075-4061&page=3",
            "ex:經典名稱": [
                "阿 (卷)"
            ],
            "ex:資料群名": "宮内庁書陵部蔵宋版大蔵経"
        },
        {
            "@id": "data:T1545_01_005-056.json#底本・校本URL",
            "ex:TEIURL": "None",
            "ex:書誌URL": "https://db2.sido.keio.ac.jp/kanseki/bib_detail?bibid=007075_0968",
            "ex:画像URL": "https://db2.sido.keio.ac.jp/kanseki/bib_frame?id=007075-4062&page=2",
            "ex:經典名稱": [
                "阿 (卷)"
            ],
            "ex:資料群名": "宮内庁書陵部蔵宋版大蔵経"
        },
        {
            "@id": "data:T1545_01_005-057.json#底本・校本URL",
            "ex:TEIURL": "None",
            "ex:書誌URL": "https://db2.sido.keio.ac.jp/kanseki/bib_detail?bibid=007075_0968",
            "ex:画像URL": "https://db2.sido.keio.ac.jp/kanseki/bib_frame?id=007075-4063&page=3",
            "ex:經典名稱": [
                "阿 (卷)"
            ],
            "ex:資料群名": "宮内庁書陵部蔵宋版大蔵経"
        },
        {
            "@id": "data:T1545_01_005-058.json#底本・校本URL",
            "ex:TEIURL": "None",
            "ex:書誌URL": "https://db2.sido.keio.ac.jp/kanseki/bib_detail?bibid=007075_0968",
            "ex:画像URL": "https://db2.sido.keio.ac.jp/kanseki/bib_frame?id=007075-4064&page=3",
            "ex:經典名稱": [
                "阿 (卷)"
            ],
            "ex:資料群名": "宮内庁書陵部蔵宋版大蔵経"
        },
        {
            "@id": "data:T1545_01_005-059.json#底本・校本URL",
            "ex:TEIURL": "None",
            "ex:書誌URL": "https://db2.sido.keio.ac.jp/kanseki/bib_detail?bibid=007075_0968",
            "ex:画像URL": "https://db2.sido.keio.ac.jp/kanseki/bib_frame?id=007075-4065&page=2",
            "ex:經典名稱": [
                "阿 (卷)"
            ],
            "ex:資料群名": "宮内庁書陵部蔵宋版大蔵経"
        },
        {
            "@id": "data:T1545_01_005-060.json#底本・校本URL",
            "ex:TEIURL": "None",
            "ex:書誌URL": "https://db2.sido.keio.ac.jp/kanseki/bib_detail?bibid=007075_0968",
            "ex:画像URL": "https://db2.sido.keio.ac.jp/kanseki/bib_frame?id=007075-4066&page=3",
            "ex:經典名稱": [
                "阿 (卷)"
            ],
            "ex:資料群名": "宮内庁書陵部蔵宋版大蔵経"
        },
        {
            "@id": "data:T1545_01_005-061.json#底本・校本URL",
            "ex:TEIURL": "None",
            "ex:書誌URL": "https://db2.sido.keio.ac.jp/kanseki/bib_detail?bibid=007075_0968",
            "ex:画像URL": "https://db2.sido.keio.ac.jp/kanseki/bib_frame?id=007075-4067&page=3",
            "ex:經典名稱": [
                "阿 (卷)"
            ],
            "ex:資料群名": "宮内庁書陵部蔵宋版大蔵経"
        },
        {
            "@id": "data:T1545_01_005-062.json#底本・校本URL",
            "ex:TEIURL": "None",
            "ex:書誌URL": "https://db2.sido.keio.ac.jp/kanseki/bib_detail?bibid=007075_0968",
            "ex:画像URL": "https://db2.sido.keio.ac.jp/kanseki/bib_frame?id=007075-4068&page=2",
            "ex:經典名稱": [
                "阿 (卷)"
            ],
            "ex:資料群名": "宮内庁書陵部蔵宋版大蔵経"
        },
        {
            "@id": "data:T1545_01_005-063.json#底本・校本URL",
            "ex:TEIURL": "None",
            "ex:書誌URL": "https://db2.sido.keio.ac.jp/kanseki/bib_detail?bibid=007075_0968",
            "ex:画像URL": "https://db2.sido.keio.ac.jp/kanseki/bib_frame?id=007075-4070&page=2",
            "ex:經典名稱": [
                "阿 (卷)"
            ],
            "ex:資料群名": "宮内庁書陵部蔵宋版大蔵経"
        },
        {
            "@id": "data:T1545_01_005-064.json#底本・校本URL",
            "ex:TEIURL": "None",
            "ex:書誌URL": "https://db2.sido.keio.ac.jp/kanseki/bib_detail?bibid=007075_0968",
            "ex:画像URL": "https://db2.sido.keio.ac.jp/kanseki/bib_frame?id=007075-4071&page=2",
            "ex:經典名稱": [
                "阿 (卷)"
            ],
            "ex:資料群名": "宮内庁書陵部蔵宋版大蔵経"
        },
        {
            "@id": "data:T1545_01_005-065.json#底本・校本URL",
            "ex:TEIURL": "None",
            "ex:書誌URL": "https://db2.sido.keio.ac.jp/kanseki/bib_detail?bibid=007075_0968",
            "ex:画像URL": "https://db2.sido.keio.ac.jp/kanseki/bib_frame?id=007075-4072&page=3",
            "ex:經典名稱": [
                "阿 (卷)"
            ],
            "ex:資料群名": "宮内庁書陵部蔵宋版大蔵経"
        },
        {
            "@id": "data:T1545_01_005-066.json#底本・校本URL",
            "ex:TEIURL": "None",
            "ex:書誌URL": "https://db2.sido.keio.ac.jp/kanseki/bib_detail?bibid=007075_0968",
            "ex:画像URL": "https://db2.sido.keio.ac.jp/kanseki/bib_frame?id=007075-4073&page=2",
            "ex:經典名稱": [
                "阿 (卷)"
            ],
            "ex:資料群名": "宮内庁書陵部蔵宋版大蔵経"
        },
        {
            "@id": "data:T1545_01_005-067.json#底本・校本URL",
            "ex:TEIURL": "None",
            "ex:書誌URL": "https://db2.sido.keio.ac.jp/kanseki/bib_detail?bibid=007075_0968",
            "ex:画像URL": "https://db2.sido.keio.ac.jp/kanseki/bib_frame?id=007075-4074&page=3",
            "ex:經典名稱": [
                "阿 (卷)"
            ],
            "ex:資料群名": "宮内庁書陵部蔵宋版大蔵経"
        },
        {
            "@id": "data:T1545_01_005-068.json#底本・校本URL",
            "ex:TEIURL": "None",
            "ex:書誌URL": "https://db2.sido.keio.ac.jp/kanseki/bib_detail?bibid=007075_0968",
            "ex:画像URL": "https://db2.sido.keio.ac.jp/kanseki/bib_frame?id=007075-4075&page=2",
            "ex:經典名稱": [
                "阿 (卷)"
            ],
            "ex:資料群名": "宮内庁書陵部蔵宋版大蔵経"
        },
        {
            "@id": "data:T1545_01_005-069.json#底本・校本URL",
            "ex:TEIURL": "None",
            "ex:書誌URL": "https://db2.sido.keio.ac.jp/kanseki/bib_detail?bibid=007075_0968",
            "ex:画像URL": "https://db2.sido.keio.ac.jp/kanseki/bib_frame?id=007075-4076&page=3",
            "ex:經典名稱": [
                "阿 (卷)"
            ],
            "ex:資料群名": "宮内庁書陵部蔵宋版大蔵経"
        },
        {
            "@id": "data:T1545_01_005-070.json#底本・校本URL",
            "ex:TEIURL": "None",
            "ex:書誌URL": "https://db2.sido.keio.ac.jp/kanseki/bib_detail?bibid=007075_0968",
            "ex:画像URL": "https://db2.sido.keio.ac.jp/kanseki/bib_frame?id=007075-4077&page=3",
            "ex:經典名稱": [
                "阿 (卷)"
            ],
            "ex:資料群名": "宮内庁書陵部蔵宋版大蔵経"
        },
        {
            "@id": "data:T1545_01_005-071.json#底本・校本URL",
            "ex:TEIURL": "None",
            "ex:書誌URL": "https://db2.sido.keio.ac.jp/kanseki/bib_detail?bibid=007075_0968",
            "ex:画像URL": "https://db2.sido.keio.ac.jp/kanseki/bib_frame?id=007075-4078&page=2",
            "ex:經典名稱": [
                "阿 (卷)"
            ],
            "ex:資料群名": "宮内庁書陵部蔵宋版大蔵経"
        },
        {
            "@id": "data:T1545_01_005-072.json#底本・校本URL",
            "ex:TEIURL": "None",
            "ex:書誌URL": "https://db2.sido.keio.ac.jp/kanseki/bib_detail?bibid=007075_0968",
            "ex:画像URL": "https://db2.sido.keio.ac.jp/kanseki/bib_frame?id=007075-4079&page=2",
            "ex:經典名稱": [
                "阿 (卷)"
            ],
            "ex:資料群名": "宮内庁書陵部蔵宋版大蔵経"
        },
        {
            "@id": "data:T1545_01_005-073.json#底本・校本URL",
            "ex:TEIURL": "None",
            "ex:書誌URL": "https://db2.sido.keio.ac.jp/kanseki/bib_detail?bibid=007075_0968",
            "ex:画像URL": "https://db2.sido.keio.ac.jp/kanseki/bib_frame?id=007075-4081&page=2",
            "ex:經典名稱": [
                "阿 (卷)"
            ],
            "ex:資料群名": "宮内庁書陵部蔵宋版大蔵経"
        },
        {
            "@id": "data:T1545_01_005-074.json#底本・校本URL",
            "ex:TEIURL": "None",
            "ex:書誌URL": "https://db2.sido.keio.ac.jp/kanseki/bib_detail?bibid=007075_0968",
            "ex:画像URL": "https://db2.sido.keio.ac.jp/kanseki/bib_frame?id=007075-4082&page=3",
            "ex:經典名稱": [
                "阿 (卷)"
            ],
            "ex:資料群名": "宮内庁書陵部蔵宋版大蔵経"
        },
        {
            "@id": "data:T1545_01_005-075.json#底本・校本URL",
            "ex:TEIURL": "None",
            "ex:書誌URL": "https://db2.sido.keio.ac.jp/kanseki/bib_detail?bibid=007075_0968",
            "ex:画像URL": "https://db2.sido.keio.ac.jp/kanseki/bib_frame?id=007075-4083&page=3",
            "ex:經典名稱": [
                "阿 (卷)"
            ],
            "ex:資料群名": "宮内庁書陵部蔵宋版大蔵経"
        },
        {
            "@id": "data:T1545_01_005-076.json#底本・校本URL",
            "ex:TEIURL": "None",
            "ex:書誌URL": "https://db2.sido.keio.ac.jp/kanseki/bib_detail?bibid=007075_0968",
            "ex:画像URL": "https://db2.sido.keio.ac.jp/kanseki/bib_frame?id=007075-4084&page=2",
            "ex:經典名稱": [
                "阿 (卷)"
            ],
            "ex:資料群名": "宮内庁書陵部蔵宋版大蔵経"
        },
        {
            "@id": "data:T1545_01_005-077.json#底本・校本URL",
            "ex:TEIURL": "None",
            "ex:書誌URL": "https://db2.sido.keio.ac.jp/kanseki/bib_detail?bibid=007075_0968",
            "ex:画像URL": "https://db2.sido.keio.ac.jp/kanseki/bib_frame?id=007075-4085&page=2",
            "ex:經典名稱": [
                "阿 (卷)"
            ],
            "ex:資料群名": "宮内庁書陵部蔵宋版大蔵経"
        },
        {
            "@id": "data:T1545_01_005-078.json#底本・校本URL",
            "ex:TEIURL": "None",
            "ex:書誌URL": "https://db2.sido.keio.ac.jp/kanseki/bib_detail?bibid=007075_0968",
            "ex:画像URL": "https://db2.sido.keio.ac.jp/kanseki/bib_frame?id=007075-4086&page=2",
            "ex:經典名稱": [
                "阿 (卷)"
            ],
            "ex:資料群名": "宮内庁書陵部蔵宋版大蔵経"
        },
        {
            "@id": "data:T1545_01_005-079.json#底本・校本URL",
            "ex:TEIURL": "None",
            "ex:書誌URL": "https://db2.sido.keio.ac.jp/kanseki/bib_detail?bibid=007075_0968",
            "ex:画像URL": "https://db2.sido.keio.ac.jp/kanseki/bib_frame?id=007075-4087&page=2",
            "ex:經典名稱": [
                "阿 (卷)"
            ],
            "ex:資料群名": "宮内庁書陵部蔵宋版大蔵経"
        },
        {
            "@id": "data:T1545_01_005-080.json#底本・校本URL",
            "ex:TEIURL": "None",
            "ex:書誌URL": "https://db2.sido.keio.ac.jp/kanseki/bib_detail?bibid=007075_0968",
            "ex:画像URL": "https://db2.sido.keio.ac.jp/kanseki/bib_frame?id=007075-4088&page=2",
            "ex:經典名稱": [
                "阿 (卷)"
            ],
            "ex:資料群名": "宮内庁書陵部蔵宋版大蔵経"
        },
        {
            "@id": "data:T1545_01_005-081.json#底本・校本URL",
            "ex:TEIURL": "None",
            "ex:書誌URL": "https://db2.sido.keio.ac.jp/kanseki/bib_detail?bibid=007075_0968",
            "ex:画像URL": "https://db2.sido.keio.ac.jp/kanseki/bib_frame?id=007075-4089&page=3",
            "ex:經典名稱": [
                "阿 (卷)"
            ],
            "ex:資料群名": "宮内庁書陵部蔵宋版大蔵経"
        },
        {
            "@id": "data:T1545_01_005-082.json#底本・校本URL",
            "ex:TEIURL": "None",
            "ex:書誌URL": "https://db2.sido.keio.ac.jp/kanseki/bib_detail?bibid=007075_0968",
            "ex:画像URL": "https://db2.sido.keio.ac.jp/kanseki/bib_frame?id=007075-4090&page=2",
            "ex:經典名稱": [
                "阿 (卷)"
            ],
            "ex:資料群名": "宮内庁書陵部蔵宋版大蔵経"
        },
        {
            "@id": "data:T1545_01_005-083.json#底本・校本URL",
            "ex:TEIURL": "None",
            "ex:書誌URL": "https://db2.sido.keio.ac.jp/kanseki/bib_detail?bibid=007075_0968",
            "ex:画像URL": "https://db2.sido.keio.ac.jp/kanseki/bib_frame?id=007075-4092&page=3",
            "ex:經典名稱": [
                "阿 (卷)"
            ],
            "ex:資料群名": "宮内庁書陵部蔵宋版大蔵経"
        },
        {
            "@id": "data:T1545_01_005-084.json#底本・校本URL",
            "ex:TEIURL": "None",
            "ex:書誌URL": "https://db2.sido.keio.ac.jp/kanseki/bib_detail?bibid=007075_0968",
            "ex:画像URL": "https://db2.sido.keio.ac.jp/kanseki/bib_frame?id=007075-4093&page=3",
            "ex:經典名稱": [
                "阿 (卷)"
            ],
            "ex:資料群名": "宮内庁書陵部蔵宋版大蔵経"
        },
        {
            "@id": "data:T1545_01_005-085.json#底本・校本URL",
            "ex:TEIURL": "None",
            "ex:書誌URL": "https://db2.sido.keio.ac.jp/kanseki/bib_detail?bibid=007075_0968",
            "ex:画像URL": "https://db2.sido.keio.ac.jp/kanseki/bib_frame?id=007075-4094&page=3",
            "ex:經典名稱": [
                "阿 (卷)"
            ],
            "ex:資料群名": "宮内庁書陵部蔵宋版大蔵経"
        },
        {
            "@id": "data:T1545_01_005-086.json#底本・校本URL",
            "ex:TEIURL": "None",
            "ex:書誌URL": "https://db2.sido.keio.ac.jp/kanseki/bib_detail?bibid=007075_0968",
            "ex:画像URL": "https://db2.sido.keio.ac.jp/kanseki/bib_frame?id=007075-4095&page=2",
            "ex:經典名稱": [
                "阿 (卷)"
            ],
            "ex:資料群名": "宮内庁書陵部蔵宋版大蔵経"
        },
        {
            "@id": "data:T1545_01_005-087.json#底本・校本URL",
            "ex:TEIURL": "None",
            "ex:書誌URL": "https://db2.sido.keio.ac.jp/kanseki/bib_detail?bibid=007075_0968",
            "ex:画像URL": "https://db2.sido.keio.ac.jp/kanseki/bib_frame?id=007075-4096&page=2",
            "ex:經典名稱": [
                "阿 (卷)"
            ],
            "ex:資料群名": "宮内庁書陵部蔵宋版大蔵経"
        },
        {
            "@id": "data:T1545_01_005-088.json#底本・校本URL",
            "ex:TEIURL": "None",
            "ex:書誌URL": "https://db2.sido.keio.ac.jp/kanseki/bib_detail?bibid=007075_0968",
            "ex:画像URL": "https://db2.sido.keio.ac.jp/kanseki/bib_frame?id=007075-4097&page=3",
            "ex:經典名稱": [
                "阿 (卷)"
            ],
            "ex:資料群名": "宮内庁書陵部蔵宋版大蔵経"
        },
        {
            "@id": "data:T1545_01_005-089.json#底本・校本URL",
            "ex:TEIURL": "None",
            "ex:書誌URL": "https://db2.sido.keio.ac.jp/kanseki/bib_detail?bibid=007075_0968",
            "ex:画像URL": "https://db2.sido.keio.ac.jp/kanseki/bib_frame?id=007075-4098&page=2",
            "ex:經典名稱": [
                "阿 (卷)"
            ],
            "ex:資料群名": "宮内庁書陵部蔵宋版大蔵経"
        },
        {
            "@id": "data:T1545_01_005-090.json#底本・校本URL",
            "ex:TEIURL": "None",
            "ex:書誌URL": "https://db2.sido.keio.ac.jp/kanseki/bib_detail?bibid=007075_0968",
            "ex:画像URL": "https://db2.sido.keio.ac.jp/kanseki/bib_frame?id=007075-4099&page=3",
            "ex:經典名稱": [
                "阿 (卷)"
            ],
            "ex:資料群名": "宮内庁書陵部蔵宋版大蔵経"
        },
        {
            "@id": "data:T1545_01_005-091.json#底本・校本URL",
            "ex:TEIURL": "None",
            "ex:書誌URL": "https://db2.sido.keio.ac.jp/kanseki/bib_detail?bibid=007075_0968",
            "ex:画像URL": "https://db2.sido.keio.ac.jp/kanseki/bib_frame?id=007075-4100&page=3",
            "ex:經典名稱": [
                "阿 (卷)"
            ],
            "ex:資料群名": "宮内庁書陵部蔵宋版大蔵経"
        },
        {
            "@id": "data:T1545_01_005-092.json#底本・校本URL",
            "ex:TEIURL": "None",
            "ex:書誌URL": "https://db2.sido.keio.ac.jp/kanseki/bib_detail?bibid=007075_0968",
            "ex:画像URL": "https://db2.sido.keio.ac.jp/kanseki/bib_frame?id=007075-4101&page=2",
            "ex:經典名稱": [
                "阿 (卷)"
            ],
            "ex:資料群名": "宮内庁書陵部蔵宋版大蔵経"
        },
        {
            "@id": "data:T1545_01_005-093.json#底本・校本URL",
            "ex:TEIURL": "None",
            "ex:書誌URL": "https://db2.sido.keio.ac.jp/kanseki/bib_detail?bibid=007075_0968",
            "ex:画像URL": "https://db2.sido.keio.ac.jp/kanseki/bib_frame?id=007075-4104&page=2",
            "ex:經典名稱": [
                "阿 (卷)"
            ],
            "ex:資料群名": "宮内庁書陵部蔵宋版大蔵経"
        },
        {
            "@id": "data:T1545_01_005-094.json#底本・校本URL",
            "ex:TEIURL": "None",
            "ex:書誌URL": "https://db2.sido.keio.ac.jp/kanseki/bib_detail?bibid=007075_0968",
            "ex:画像URL": "https://db2.sido.keio.ac.jp/kanseki/bib_frame?id=007075-4105&page=3",
            "ex:經典名稱": [
                "阿 (卷)"
            ],
            "ex:資料群名": "宮内庁書陵部蔵宋版大蔵経"
        },
        {
            "@id": "data:T1545_01_005-095.json#底本・校本URL",
            "ex:TEIURL": "None",
            "ex:書誌URL": "https://db2.sido.keio.ac.jp/kanseki/bib_detail?bibid=007075_0968",
            "ex:画像URL": "https://db2.sido.keio.ac.jp/kanseki/bib_frame?id=007075-4106&page=2",
            "ex:經典名稱": [
                "阿 (卷)"
            ],
            "ex:資料群名": "宮内庁書陵部蔵宋版大蔵経"
        },
        {
            "@id": "data:T1545_01_005-096.json#底本・校本URL",
            "ex:TEIURL": "None",
            "ex:書誌URL": "https://db2.sido.keio.ac.jp/kanseki/bib_detail?bibid=007075_0968",
            "ex:画像URL": "https://db2.sido.keio.ac.jp/kanseki/bib_frame?id=007075-4107&page=2",
            "ex:經典名稱": [
                "阿 (卷)"
            ],
            "ex:資料群名": "宮内庁書陵部蔵宋版大蔵経"
        },
        {
            "@id": "data:T1545_01_005-097.json#底本・校本URL",
            "ex:TEIURL": "None",
            "ex:書誌URL": "https://db2.sido.keio.ac.jp/kanseki/bib_detail?bibid=007075_0968",
            "ex:画像URL": "https://db2.sido.keio.ac.jp/kanseki/bib_frame?id=007075-4108&page=2",
            "ex:經典名稱": [
                "阿 (卷)"
            ],
            "ex:資料群名": "宮内庁書陵部蔵宋版大蔵経"
        },
        {
            "@id": "data:T1545_01_005-098.json#底本・校本URL",
            "ex:TEIURL": "None",
            "ex:書誌URL": "https://db2.sido.keio.ac.jp/kanseki/bib_detail?bibid=007075_0968",
            "ex:画像URL": "https://db2.sido.keio.ac.jp/kanseki/bib_frame?id=007075-4109&page=2",
            "ex:經典名稱": [
                "阿 (卷)"
            ],
            "ex:資料群名": "宮内庁書陵部蔵宋版大蔵経"
        },
        {
            "@id": "data:T1545_01_005-099.json#底本・校本URL",
            "ex:TEIURL": "None",
            "ex:書誌URL": "https://db2.sido.keio.ac.jp/kanseki/bib_detail?bibid=007075_0968",
            "ex:画像URL": "https://db2.sido.keio.ac.jp/kanseki/bib_frame?id=007075-4110&page=2",
            "ex:經典名稱": [
                "阿 (卷)"
            ],
            "ex:資料群名": "宮内庁書陵部蔵宋版大蔵経"
        },
        {
            "@id": "data:T1545_01_005-100.json#底本・校本URL",
            "ex:TEIURL": "None",
            "ex:書誌URL": "https://db2.sido.keio.ac.jp/kanseki/bib_detail?bibid=007075_0968",
            "ex:画像URL": "https://db2.sido.keio.ac.jp/kanseki/bib_frame?id=007075-4111&page=2",
            "ex:經典名稱": [
                "阿 (卷)"
            ],
            "ex:資料群名": "宮内庁書陵部蔵宋版大蔵経"
        },
        {
            "@id": "data:T1545_01_005-101.json#底本・校本URL",
            "ex:TEIURL": "None",
            "ex:書誌URL": "https://db2.sido.keio.ac.jp/kanseki/bib_detail?bibid=007075_0968",
            "ex:画像URL": "https://db2.sido.keio.ac.jp/kanseki/bib_frame?id=007075-4112&page=2",
            "ex:經典名稱": [
                "阿 (卷)"
            ],
            "ex:資料群名": "宮内庁書陵部蔵宋版大蔵経"
        },
        {
            "@id": "data:T1545_01_005-102.json#底本・校本URL",
            "ex:TEIURL": "None",
            "ex:書誌URL": "https://db2.sido.keio.ac.jp/kanseki/bib_detail?bibid=007075_0968",
            "ex:画像URL": "https://db2.sido.keio.ac.jp/kanseki/bib_frame?id=007075-4113&page=2",
            "ex:經典名稱": [
                "阿 (卷)"
            ],
            "ex:資料群名": "宮内庁書陵部蔵宋版大蔵経"
        },
        {
            "@id": "data:T1545_01_005-103.json#底本・校本URL",
            "ex:TEIURL": "None",
            "ex:書誌URL": "https://db2.sido.keio.ac.jp/kanseki/bib_detail?bibid=007075_0968",
            "ex:画像URL": "https://db2.sido.keio.ac.jp/kanseki/bib_frame?id=007075-4114&page=3",
            "ex:經典名稱": [
                "阿 (卷)"
            ],
            "ex:資料群名": "宮内庁書陵部蔵宋版大蔵経"
        },
        {
            "@id": "data:T1545_01_005-104.json#底本・校本URL",
            "ex:TEIURL": "None",
            "ex:書誌URL": "https://db2.sido.keio.ac.jp/kanseki/bib_detail?bibid=007075_0968",
            "ex:画像URL": "https://db2.sido.keio.ac.jp/kanseki/bib_frame?id=007075-4115&page=2",
            "ex:經典名稱": [
                "阿 (卷)"
            ],
            "ex:資料群名": "宮内庁書陵部蔵宋版大蔵経"
        },
        {
            "@id": "data:T1545_01_005-105.json#底本・校本URL",
            "ex:TEIURL": "None",
            "ex:書誌URL": "https://db2.sido.keio.ac.jp/kanseki/bib_detail?bibid=007075_0968",
            "ex:画像URL": "https://db2.sido.keio.ac.jp/kanseki/bib_frame?id=007075-4117&page=2",
            "ex:經典名稱": [
                "阿 (卷)"
            ],
            "ex:資料群名": "宮内庁書陵部蔵宋版大蔵経"
        },
        {
            "@id": "data:T1545_01_005-106.json#底本・校本URL",
            "ex:TEIURL": "None",
            "ex:書誌URL": "https://db2.sido.keio.ac.jp/kanseki/bib_detail?bibid=007075_0968",
            "ex:画像URL": "https://db2.sido.keio.ac.jp/kanseki/bib_frame?id=007075-4118&page=2",
            "ex:經典名稱": [
                "阿 (卷)"
            ],
            "ex:資料群名": "宮内庁書陵部蔵宋版大蔵経"
        },
        {
            "@id": "data:T1545_01_005-107.json#底本・校本URL",
            "ex:TEIURL": "None",
            "ex:書誌URL": "https://db2.sido.keio.ac.jp/kanseki/bib_detail?bibid=007075_0968",
            "ex:画像URL": "https://db2.sido.keio.ac.jp/kanseki/bib_frame?id=007075-4119&page=3",
            "ex:經典名稱": [
                "阿 (卷)"
            ],
            "ex:資料群名": "宮内庁書陵部蔵宋版大蔵経"
        },
        {
            "@id": "data:T1545_01_005-108.json#底本・校本URL",
            "ex:TEIURL": "None",
            "ex:書誌URL": "https://db2.sido.keio.ac.jp/kanseki/bib_detail?bibid=007075_0968",
            "ex:画像URL": "https://db2.sido.keio.ac.jp/kanseki/bib_frame?id=007075-4120&page=2",
            "ex:經典名稱": [
                "阿 (卷)"
            ],
            "ex:資料群名": "宮内庁書陵部蔵宋版大蔵経"
        },
        {
            "@id": "data:T1545_01_005-109.json#底本・校本URL",
            "ex:TEIURL": "None",
            "ex:書誌URL": "https://db2.sido.keio.ac.jp/kanseki/bib_detail?bibid=007075_0968",
            "ex:画像URL": "https://db2.sido.keio.ac.jp/kanseki/bib_frame?id=007075-4121&page=2",
            "ex:經典名稱": [
                "阿 (卷)"
            ],
            "ex:資料群名": "宮内庁書陵部蔵宋版大蔵経"
        },
        {
            "@id": "data:T1545_01_005-110.json#底本・校本URL",
            "ex:TEIURL": "None",
            "ex:書誌URL": "https://db2.sido.keio.ac.jp/kanseki/bib_detail?bibid=007075_0968",
            "ex:画像URL": "https://db2.sido.keio.ac.jp/kanseki/bib_frame?id=007075-4122&page=3",
            "ex:經典名稱": [
                "阿 (卷)"
            ],
            "ex:資料群名": "宮内庁書陵部蔵宋版大蔵経"
        },
        {
            "@id": "data:T1545_01_005-111.json#底本・校本URL",
            "ex:TEIURL": "None",
            "ex:書誌URL": "https://db2.sido.keio.ac.jp/kanseki/bib_detail?bibid=007075_0968",
            "ex:画像URL": "https://db2.sido.keio.ac.jp/kanseki/bib_frame?id=007075-4123&page=2",
            "ex:經典名稱": [
                "阿 (卷)"
            ],
            "ex:資料群名": "宮内庁書陵部蔵宋版大蔵経"
        },
        {
            "@id": "data:T1545_01_005-112.json#底本・校本URL",
            "ex:TEIURL": "None",
            "ex:書誌URL": "https://db2.sido.keio.ac.jp/kanseki/bib_detail?bibid=007075_0968",
            "ex:画像URL": "https://db2.sido.keio.ac.jp/kanseki/bib_frame?id=007075-4124&page=2",
            "ex:經典名稱": [
                "阿 (卷)"
            ],
            "ex:資料群名": "宮内庁書陵部蔵宋版大蔵経"
        },
        {
            "@id": "data:T1545_01_005-113.json#底本・校本URL",
            "ex:TEIURL": "None",
            "ex:書誌URL": "https://db2.sido.keio.ac.jp/kanseki/bib_detail?bibid=007075_0968",
            "ex:画像URL": "https://db2.sido.keio.ac.jp/kanseki/bib_frame?id=007075-4125&page=3",
            "ex:經典名稱": [
                "阿 (卷)"
            ],
            "ex:資料群名": "宮内庁書陵部蔵宋版大蔵経"
        },
        {
            "@id": "data:T1545_01_005-114.json#底本・校本URL",
            "ex:TEIURL": "None",
            "ex:書誌URL": "https://db2.sido.keio.ac.jp/kanseki/bib_detail?bibid=007075_0968",
            "ex:画像URL": "https://db2.sido.keio.ac.jp/kanseki/bib_frame?id=007075-4126&page=2",
            "ex:經典名稱": [
                "阿 (卷)"
            ],
            "ex:資料群名": "宮内庁書陵部蔵宋版大蔵経"
        },
        {
            "@id": "data:T1545_01_005-115.json#底本・校本URL",
            "ex:TEIURL": "None",
            "ex:書誌URL": "https://db2.sido.keio.ac.jp/kanseki/bib_detail?bibid=007075_0968",
            "ex:画像URL": "https://db2.sido.keio.ac.jp/kanseki/bib_frame?id=007075-4128&page=3",
            "ex:經典名稱": [
                "阿 (卷)"
            ],
            "ex:資料群名": "宮内庁書陵部蔵宋版大蔵経"
        },
        {
            "@id": "data:T1545_01_005-116.json#底本・校本URL",
            "ex:TEIURL": "None",
            "ex:書誌URL": "https://db2.sido.keio.ac.jp/kanseki/bib_detail?bibid=007075_0968",
            "ex:画像URL": "https://db2.sido.keio.ac.jp/kanseki/bib_frame?id=007075-4129&page=3",
            "ex:經典名稱": [
                "阿 (卷)"
            ],
            "ex:資料群名": "宮内庁書陵部蔵宋版大蔵経"
        },
        {
            "@id": "data:T1545_01_005-117.json#底本・校本URL",
            "ex:TEIURL": "None",
            "ex:書誌URL": "https://db2.sido.keio.ac.jp/kanseki/bib_detail?bibid=007075_0968",
            "ex:画像URL": "https://db2.sido.keio.ac.jp/kanseki/bib_frame?id=007075-4130&page=3",
            "ex:經典名稱": [
                "阿 (卷)"
            ],
            "ex:資料群名": "宮内庁書陵部蔵宋版大蔵経"
        },
        {
            "@id": "data:T1545_01_005-118.json#底本・校本URL",
            "ex:TEIURL": "None",
            "ex:書誌URL": "https://db2.sido.keio.ac.jp/kanseki/bib_detail?bibid=007075_0968",
            "ex:画像URL": "https://db2.sido.keio.ac.jp/kanseki/bib_frame?id=007075-4131&page=3",
            "ex:經典名稱": [
                "阿 (卷)"
            ],
            "ex:資料群名": "宮内庁書陵部蔵宋版大蔵経"
        },
        {
            "@id": "data:T1545_01_005-119.json#底本・校本URL",
            "ex:TEIURL": "None",
            "ex:書誌URL": "https://db2.sido.keio.ac.jp/kanseki/bib_detail?bibid=007075_0968",
            "ex:画像URL": "https://db2.sido.keio.ac.jp/kanseki/bib_frame?id=007075-4132&page=2",
            "ex:經典名稱": [
                "阿 (卷)"
            ],
            "ex:資料群名": "宮内庁書陵部蔵宋版大蔵経"
        },
        {
            "@id": "data:T1545_01_005-120.json#底本・校本URL",
            "ex:TEIURL": "None",
            "ex:書誌URL": "https://db2.sido.keio.ac.jp/kanseki/bib_detail?bibid=007075_0968",
            "ex:画像URL": "https://db2.sido.keio.ac.jp/kanseki/bib_frame?id=007075-4133&page=3",
            "ex:經典名稱": [
                "阿 (卷)"
            ],
            "ex:資料群名": "宮内庁書陵部蔵宋版大蔵経"
        },
        {
            "@id": "data:T1545_01_005-121.json#底本・校本URL",
            "ex:TEIURL": "None",
            "ex:書誌URL": "https://db2.sido.keio.ac.jp/kanseki/bib_detail?bibid=007075_0968",
            "ex:画像URL": "https://db2.sido.keio.ac.jp/kanseki/bib_frame?id=007075-4134&page=2",
            "ex:經典名稱": [
                "阿 (卷)"
            ],
            "ex:資料群名": "宮内庁書陵部蔵宋版大蔵経"
        },
        {
            "@id": "data:T1545_01_005-122.json#底本・校本URL",
            "ex:TEIURL": "None",
            "ex:書誌URL": "https://db2.sido.keio.ac.jp/kanseki/bib_detail?bibid=007075_0968",
            "ex:画像URL": "https://db2.sido.keio.ac.jp/kanseki/bib_frame?id=007075-4135&page=3",
            "ex:經典名稱": [
                "阿 (卷)"
            ],
            "ex:資料群名": "宮内庁書陵部蔵宋版大蔵経"
        },
        {
            "@id": "data:T1545_01_005-123.json#底本・校本URL",
            "ex:TEIURL": "None",
            "ex:書誌URL": "https://db2.sido.keio.ac.jp/kanseki/bib_detail?bibid=007075_0968",
            "ex:画像URL": "https://db2.sido.keio.ac.jp/kanseki/bib_frame?id=007075-4136&page=3",
            "ex:經典名稱": [
                "阿 (卷)"
            ],
            "ex:資料群名": "宮内庁書陵部蔵宋版大蔵経"
        },
        {
            "@id": "data:T1545_01_005-124.json#底本・校本URL",
            "ex:TEIURL": "None",
            "ex:書誌URL": "https://db2.sido.keio.ac.jp/kanseki/bib_detail?bibid=007075_0968",
            "ex:画像URL": "https://db2.sido.keio.ac.jp/kanseki/bib_frame?id=007075-4137&page=2",
            "ex:經典名稱": [
                "阿 (卷)"
            ],
            "ex:資料群名": "宮内庁書陵部蔵宋版大蔵経"
        },
        {
            "@id": "data:T1545_01_005-125.json#底本・校本URL",
            "ex:TEIURL": "None",
            "ex:書誌URL": "https://db2.sido.keio.ac.jp/kanseki/bib_detail?bibid=007075_0968",
            "ex:画像URL": "https://db2.sido.keio.ac.jp/kanseki/bib_frame?id=007075-4139&page=2",
            "ex:經典名稱": [
                "阿 (卷)"
            ],
            "ex:資料群名": "宮内庁書陵部蔵宋版大蔵経"
        },
        {
            "@id": "data:T1545_01_005-126.json#底本・校本URL",
            "ex:TEIURL": "None",
            "ex:書誌URL": "https://db2.sido.keio.ac.jp/kanseki/bib_detail?bibid=007075_0968",
            "ex:画像URL": "https://db2.sido.keio.ac.jp/kanseki/bib_frame?id=007075-4140&page=2",
            "ex:經典名稱": [
                "阿 (卷)"
            ],
            "ex:資料群名": "宮内庁書陵部蔵宋版大蔵経"
        },
        {
            "@id": "data:T1545_01_005-127.json#底本・校本URL",
            "ex:TEIURL": "None",
            "ex:書誌URL": "https://db2.sido.keio.ac.jp/kanseki/bib_detail?bibid=007075_0968",
            "ex:画像URL": "https://db2.sido.keio.ac.jp/kanseki/bib_frame?id=007075-4141&page=2",
            "ex:經典名稱": [
                "阿 (卷)"
            ],
            "ex:資料群名": "宮内庁書陵部蔵宋版大蔵経"
        },
        {
            "@id": "data:T1545_01_005-128.json#底本・校本URL",
            "ex:TEIURL": "None",
            "ex:書誌URL": "https://db2.sido.keio.ac.jp/kanseki/bib_detail?bibid=007075_0968",
            "ex:画像URL": "https://db2.sido.keio.ac.jp/kanseki/bib_frame?id=007075-4142&page=2",
            "ex:經典名稱": [
                "阿 (卷)"
            ],
            "ex:資料群名": "宮内庁書陵部蔵宋版大蔵経"
        },
        {
            "@id": "data:T1545_01_005-129.json#底本・校本URL",
            "ex:TEIURL": "None",
            "ex:書誌URL": "https://db2.sido.keio.ac.jp/kanseki/bib_detail?bibid=007075_0968",
            "ex:画像URL": "https://db2.sido.keio.ac.jp/kanseki/bib_frame?id=007075-4143&page=3",
            "ex:經典名稱": [
                "阿 (卷)"
            ],
            "ex:資料群名": "宮内庁書陵部蔵宋版大蔵経"
        },
        {
            "@id": "data:T1545_01_005-130.json#底本・校本URL",
            "ex:TEIURL": "None",
            "ex:書誌URL": "https://db2.sido.keio.ac.jp/kanseki/bib_detail?bibid=007075_0968",
            "ex:画像URL": "https://db2.sido.keio.ac.jp/kanseki/bib_frame?id=007075-4144&page=3",
            "ex:經典名稱": [
                "阿 (卷)"
            ],
            "ex:資料群名": "宮内庁書陵部蔵宋版大蔵経"
        },
        {
            "@id": "data:T1545_01_005-131.json#底本・校本URL",
            "ex:TEIURL": "None",
            "ex:書誌URL": "https://db2.sido.keio.ac.jp/kanseki/bib_detail?bibid=007075_0968",
            "ex:画像URL": "https://db2.sido.keio.ac.jp/kanseki/bib_frame?id=007075-4145&page=3",
            "ex:經典名稱": [
                "阿 (卷)"
            ],
            "ex:資料群名": "宮内庁書陵部蔵宋版大蔵経"
        },
        {
            "@id": "data:T1545_01_005-132.json#底本・校本URL",
            "ex:TEIURL": "None",
            "ex:書誌URL": "https://db2.sido.keio.ac.jp/kanseki/bib_detail?bibid=007075_0968",
            "ex:画像URL": "https://db2.sido.keio.ac.jp/kanseki/bib_frame?id=007075-4146&page=3",
            "ex:經典名稱": [
                "阿 (卷)"
            ],
            "ex:資料群名": "宮内庁書陵部蔵宋版大蔵経"
        },
        {
            "@id": "data:T1545_01_005-133.json#底本・校本URL",
            "ex:TEIURL": "None",
            "ex:書誌URL": "https://db2.sido.keio.ac.jp/kanseki/bib_detail?bibid=007075_0968",
            "ex:画像URL": "https://db2.sido.keio.ac.jp/kanseki/bib_frame?id=007075-4147&page=3",
            "ex:經典名稱": [
                "阿 (卷)"
            ],
            "ex:資料群名": "宮内庁書陵部蔵宋版大蔵経"
        },
        {
            "@id": "data:T1545_01_005-134.json#底本・校本URL",
            "ex:TEIURL": "None",
            "ex:書誌URL": "https://db2.sido.keio.ac.jp/kanseki/bib_detail?bibid=007075_0968",
            "ex:画像URL": "https://db2.sido.keio.ac.jp/kanseki/bib_frame?id=007075-4148&page=3",
            "ex:經典名稱": [
                "阿 (卷)"
            ],
            "ex:資料群名": "宮内庁書陵部蔵宋版大蔵経"
        },
        {
            "@id": "data:T1545_01_005-135.json#底本・校本URL",
            "ex:TEIURL": "None",
            "ex:書誌URL": "https://db2.sido.keio.ac.jp/kanseki/bib_detail?bibid=007075_0968",
            "ex:画像URL": "https://db2.sido.keio.ac.jp/kanseki/bib_frame?id=007075-4150&page=3",
            "ex:經典名稱": [
                "阿 (卷)"
            ],
            "ex:資料群名": "宮内庁書陵部蔵宋版大蔵経"
        },
        {
            "@id": "data:T1545_01_005-136.json#底本・校本URL",
            "ex:TEIURL": "None",
            "ex:書誌URL": "https://db2.sido.keio.ac.jp/kanseki/bib_detail?bibid=007075_0968",
            "ex:画像URL": "https://db2.sido.keio.ac.jp/kanseki/bib_frame?id=007075-4151&page=2",
            "ex:經典名稱": [
                "阿 (卷)"
            ],
            "ex:資料群名": "宮内庁書陵部蔵宋版大蔵経"
        },
        {
            "@id": "data:T1545_01_005-137.json#底本・校本URL",
            "ex:TEIURL": "None",
            "ex:書誌URL": "https://db2.sido.keio.ac.jp/kanseki/bib_detail?bibid=007075_0968",
            "ex:画像URL": "https://db2.sido.keio.ac.jp/kanseki/bib_frame?id=007075-4152&page=3",
            "ex:經典名稱": [
                "阿 (卷)"
            ],
            "ex:資料群名": "宮内庁書陵部蔵宋版大蔵経"
        },
        {
            "@id": "data:T1545_01_005-138.json#底本・校本URL",
            "ex:TEIURL": "None",
            "ex:書誌URL": "https://db2.sido.keio.ac.jp/kanseki/bib_detail?bibid=007075_0968",
            "ex:画像URL": "https://db2.sido.keio.ac.jp/kanseki/bib_frame?id=007075-4153&page=3",
            "ex:經典名稱": [
                "阿 (卷)"
            ],
            "ex:資料群名": "宮内庁書陵部蔵宋版大蔵経"
        },
        {
            "@id": "data:T1545_01_005-139.json#底本・校本URL",
            "ex:TEIURL": "None",
            "ex:書誌URL": "https://db2.sido.keio.ac.jp/kanseki/bib_detail?bibid=007075_0968",
            "ex:画像URL": "https://db2.sido.keio.ac.jp/kanseki/bib_frame?id=007075-4154&page=3",
            "ex:經典名稱": [
                "阿 (卷)"
            ],
            "ex:資料群名": "宮内庁書陵部蔵宋版大蔵経"
        },
        {
            "@id": "data:T1545_01_005-140.json#底本・校本URL",
            "ex:TEIURL": "None",
            "ex:書誌URL": "https://db2.sido.keio.ac.jp/kanseki/bib_detail?bibid=007075_0968",
            "ex:画像URL": "https://db2.sido.keio.ac.jp/kanseki/bib_frame?id=007075-4155&page=2",
            "ex:經典名稱": [
                "阿 (卷)"
            ],
            "ex:資料群名": "宮内庁書陵部蔵宋版大蔵経"
        },
        {
            "@id": "data:T1545_01_005-141.json#底本・校本URL",
            "ex:TEIURL": "None",
            "ex:書誌URL": "https://db2.sido.keio.ac.jp/kanseki/bib_detail?bibid=007075_0968",
            "ex:画像URL": "https://db2.sido.keio.ac.jp/kanseki/bib_frame?id=007075-4156&page=2",
            "ex:經典名稱": [
                "阿 (卷)"
            ],
            "ex:資料群名": "宮内庁書陵部蔵宋版大蔵経"
        },
        {
            "@id": "data:T1545_01_005-142.json#底本・校本URL",
            "ex:TEIURL": "None",
            "ex:書誌URL": "https://db2.sido.keio.ac.jp/kanseki/bib_detail?bibid=007075_0968",
            "ex:画像URL": "https://db2.sido.keio.ac.jp/kanseki/bib_frame?id=007075-4157&page=2",
            "ex:經典名稱": [
                "阿 (卷)"
            ],
            "ex:資料群名": "宮内庁書陵部蔵宋版大蔵経"
        },
        {
            "@id": "data:T1545_01_005-143.json#底本・校本URL",
            "ex:TEIURL": "None",
            "ex:書誌URL": "https://db2.sido.keio.ac.jp/kanseki/bib_detail?bibid=007075_0968",
            "ex:画像URL": "https://db2.sido.keio.ac.jp/kanseki/bib_frame?id=007075-4158&page=2",
            "ex:經典名稱": [
                "阿 (卷)"
            ],
            "ex:資料群名": "宮内庁書陵部蔵宋版大蔵経"
        },
        {
            "@id": "data:T1545_01_005-144.json#底本・校本URL",
            "ex:TEIURL": "None",
            "ex:書誌URL": "https://db2.sido.keio.ac.jp/kanseki/bib_detail?bibid=007075_0968",
            "ex:画像URL": "https://db2.sido.keio.ac.jp/kanseki/bib_frame?id=007075-4159&page=2",
            "ex:經典名稱": [
                "阿 (卷)"
            ],
            "ex:資料群名": "宮内庁書陵部蔵宋版大蔵経"
        },
        {
            "@id": "data:T1545_01_005-145.json#底本・校本URL",
            "ex:TEIURL": "None",
            "ex:書誌URL": "https://db2.sido.keio.ac.jp/kanseki/bib_detail?bibid=007075_0968",
            "ex:画像URL": "https://db2.sido.keio.ac.jp/kanseki/bib_frame?id=007075-4161&page=2",
            "ex:經典名稱": [
                "阿 (卷)"
            ],
            "ex:資料群名": "宮内庁書陵部蔵宋版大蔵経"
        },
        {
            "@id": "data:T1545_01_005-146.json#底本・校本URL",
            "ex:TEIURL": "None",
            "ex:書誌URL": "https://db2.sido.keio.ac.jp/kanseki/bib_detail?bibid=007075_0968",
            "ex:画像URL": "https://db2.sido.keio.ac.jp/kanseki/bib_frame?id=007075-4162&page=3",
            "ex:經典名稱": [
                "阿 (卷)"
            ],
            "ex:資料群名": "宮内庁書陵部蔵宋版大蔵経"
        },
        {
            "@id": "data:T1545_01_005-147.json#底本・校本URL",
            "ex:TEIURL": "None",
            "ex:書誌URL": "https://db2.sido.keio.ac.jp/kanseki/bib_detail?bibid=007075_0968",
            "ex:画像URL": "https://db2.sido.keio.ac.jp/kanseki/bib_frame?id=007075-4163&page=2",
            "ex:經典名稱": [
                "阿 (卷)"
            ],
            "ex:資料群名": "宮内庁書陵部蔵宋版大蔵経"
        },
        {
            "@id": "data:T1545_01_005-148.json#底本・校本URL",
            "ex:TEIURL": "None",
            "ex:書誌URL": "https://db2.sido.keio.ac.jp/kanseki/bib_detail?bibid=007075_0968",
            "ex:画像URL": "https://db2.sido.keio.ac.jp/kanseki/bib_frame?id=007075-4164&page=3",
            "ex:經典名稱": [
                "阿 (卷)"
            ],
            "ex:資料群名": "宮内庁書陵部蔵宋版大蔵経"
        },
        {
            "@id": "data:T1545_01_005-149.json#底本・校本URL",
            "ex:TEIURL": "None",
            "ex:書誌URL": "https://db2.sido.keio.ac.jp/kanseki/bib_detail?bibid=007075_0968",
            "ex:画像URL": "https://db2.sido.keio.ac.jp/kanseki/bib_frame?id=007075-4165&page=2",
            "ex:經典名稱": [
                "阿 (卷)"
            ],
            "ex:資料群名": "宮内庁書陵部蔵宋版大蔵経"
        },
        {
            "@id": "data:T1545_01_005-150.json#底本・校本URL",
            "ex:TEIURL": "None",
            "ex:書誌URL": "https://db2.sido.keio.ac.jp/kanseki/bib_detail?bibid=007075_0968",
            "ex:画像URL": "https://db2.sido.keio.ac.jp/kanseki/bib_frame?id=007075-4166&page=2",
            "ex:經典名稱": [
                "阿 (卷)"
            ],
            "ex:資料群名": "宮内庁書陵部蔵宋版大蔵経"
        },
        {
            "@id": "data:T1545_01_005-151.json#底本・校本URL",
            "ex:TEIURL": "None",
            "ex:書誌URL": "https://db2.sido.keio.ac.jp/kanseki/bib_detail?bibid=007075_0968",
            "ex:画像URL": "https://db2.sido.keio.ac.jp/kanseki/bib_frame?id=007075-4167&page=2",
            "ex:經典名稱": [
                "阿 (卷)"
            ],
            "ex:資料群名": "宮内庁書陵部蔵宋版大蔵経"
        },
        {
            "@id": "data:T1545_01_005-152.json#底本・校本URL",
            "ex:TEIURL": "None",
            "ex:書誌URL": "https://db2.sido.keio.ac.jp/kanseki/bib_detail?bibid=007075_0968",
            "ex:画像URL": "https://db2.sido.keio.ac.jp/kanseki/bib_frame?id=007075-4168&page=3",
            "ex:經典名稱": [
                "阿 (卷)"
            ],
            "ex:資料群名": "宮内庁書陵部蔵宋版大蔵経"
        },
        {
            "@id": "data:T1545_01_005-153.json#底本・校本URL",
            "ex:TEIURL": "None",
            "ex:書誌URL": "https://db2.sido.keio.ac.jp/kanseki/bib_detail?bibid=007075_0968",
            "ex:画像URL": "https://db2.sido.keio.ac.jp/kanseki/bib_frame?id=007075-4169&page=3",
            "ex:經典名稱": [
                "阿 (卷)"
            ],
            "ex:資料群名": "宮内庁書陵部蔵宋版大蔵経"
        },
        {
            "@id": "data:T1545_01_005-154.json#底本・校本URL",
            "ex:TEIURL": "None",
            "ex:書誌URL": "https://db2.sido.keio.ac.jp/kanseki/bib_detail?bibid=007075_0968",
            "ex:画像URL": "https://db2.sido.keio.ac.jp/kanseki/bib_frame?id=007075-4170&page=2",
            "ex:經典名稱": [
                "阿 (卷)"
            ],
            "ex:資料群名": "宮内庁書陵部蔵宋版大蔵経"
        },
        {
            "@id": "data:T1545_01_005-155.json#底本・校本URL",
            "ex:TEIURL": "None",
            "ex:書誌URL": "https://db2.sido.keio.ac.jp/kanseki/bib_detail?bibid=007075_0968",
            "ex:画像URL": "https://db2.sido.keio.ac.jp/kanseki/bib_frame?id=007075-4172&page=2",
            "ex:經典名稱": [
                "阿 (卷)"
            ],
            "ex:資料群名": "宮内庁書陵部蔵宋版大蔵経"
        },
        {
            "@id": "data:T1545_01_005-156.json#底本・校本URL",
            "ex:TEIURL": "None",
            "ex:書誌URL": "https://db2.sido.keio.ac.jp/kanseki/bib_detail?bibid=007075_0968",
            "ex:画像URL": "https://db2.sido.keio.ac.jp/kanseki/bib_frame?id=007075-4173&page=3",
            "ex:經典名稱": [
                "阿 (卷)"
            ],
            "ex:資料群名": "宮内庁書陵部蔵宋版大蔵経"
        },
        {
            "@id": "data:T1545_01_005-157.json#底本・校本URL",
            "ex:TEIURL": "None",
            "ex:書誌URL": "https://db2.sido.keio.ac.jp/kanseki/bib_detail?bibid=007075_0968",
            "ex:画像URL": "https://db2.sido.keio.ac.jp/kanseki/bib_frame?id=007075-4174&page=2",
            "ex:經典名稱": [
                "阿 (卷)"
            ],
            "ex:資料群名": "宮内庁書陵部蔵宋版大蔵経"
        },
        {
            "@id": "data:T1545_01_005-158.json#底本・校本URL",
            "ex:TEIURL": "None",
            "ex:書誌URL": "https://db2.sido.keio.ac.jp/kanseki/bib_detail?bibid=007075_0968",
            "ex:画像URL": "https://db2.sido.keio.ac.jp/kanseki/bib_frame?id=007075-4175&page=3",
            "ex:經典名稱": [
                "阿 (卷)"
            ],
            "ex:資料群名": "宮内庁書陵部蔵宋版大蔵経"
        },
        {
            "@id": "data:T1545_01_005-159.json#底本・校本URL",
            "ex:TEIURL": "None",
            "ex:書誌URL": "https://db2.sido.keio.ac.jp/kanseki/bib_detail?bibid=007075_0968",
            "ex:画像URL": "https://db2.sido.keio.ac.jp/kanseki/bib_frame?id=007075-4176&page=3",
            "ex:經典名稱": [
                "阿 (卷)"
            ],
            "ex:資料群名": "宮内庁書陵部蔵宋版大蔵経"
        },
        {
            "@id": "data:T1545_01_005-160.json#底本・校本URL",
            "ex:TEIURL": "None",
            "ex:書誌URL": "https://db2.sido.keio.ac.jp/kanseki/bib_detail?bibid=007075_0968",
            "ex:画像URL": "https://db2.sido.keio.ac.jp/kanseki/bib_frame?id=007075-4177&page=2",
            "ex:經典名稱": [
                "阿 (卷)"
            ],
            "ex:資料群名": "宮内庁書陵部蔵宋版大蔵経"
        },
        {
            "@id": "data:T1545_01_005-161.json#底本・校本URL",
            "ex:TEIURL": "None",
            "ex:書誌URL": "https://db2.sido.keio.ac.jp/kanseki/bib_detail?bibid=007075_0968",
            "ex:画像URL": "https://db2.sido.keio.ac.jp/kanseki/bib_frame?id=007075-4178&page=2",
            "ex:經典名稱": [
                "阿 (卷)"
            ],
            "ex:資料群名": "宮内庁書陵部蔵宋版大蔵経"
        },
        {
            "@id": "data:T1545_01_005-162.json#底本・校本URL",
            "ex:TEIURL": "None",
            "ex:書誌URL": "https://db2.sido.keio.ac.jp/kanseki/bib_detail?bibid=007075_0968",
            "ex:画像URL": "https://db2.sido.keio.ac.jp/kanseki/bib_frame?id=007075-4179&page=2",
            "ex:經典名稱": [
                "阿 (卷)"
            ],
            "ex:資料群名": "宮内庁書陵部蔵宋版大蔵経"
        },
        {
            "@id": "data:T1545_01_005-163.json#底本・校本URL",
            "ex:TEIURL": "None",
            "ex:書誌URL": "https://db2.sido.keio.ac.jp/kanseki/bib_detail?bibid=007075_0968",
            "ex:画像URL": "https://db2.sido.keio.ac.jp/kanseki/bib_frame?id=007075-4180&page=3",
            "ex:經典名稱": [
                "阿 (卷)"
            ],
            "ex:資料群名": "宮内庁書陵部蔵宋版大蔵経"
        },
        {
            "@id": "data:T1545_01_005-164.json#底本・校本URL",
            "ex:TEIURL": "None",
            "ex:書誌URL": "https://db2.sido.keio.ac.jp/kanseki/bib_detail?bibid=007075_0968",
            "ex:画像URL": "https://db2.sido.keio.ac.jp/kanseki/bib_frame?id=007075-4181&page=3",
            "ex:經典名稱": [
                "阿 (卷)"
            ],
            "ex:資料群名": "宮内庁書陵部蔵宋版大蔵経"
        },
        {
            "@id": "data:T1545_01_005-165.json#底本・校本URL",
            "ex:TEIURL": "None",
            "ex:書誌URL": "https://db2.sido.keio.ac.jp/kanseki/bib_detail?bibid=007075_0968",
            "ex:画像URL": "https://db2.sido.keio.ac.jp/kanseki/bib_frame?id=007075-4183&page=3",
            "ex:經典名稱": [
                "阿 (卷)"
            ],
            "ex:資料群名": "宮内庁書陵部蔵宋版大蔵経"
        },
        {
            "@id": "data:T1545_01_005-166.json#底本・校本URL",
            "ex:TEIURL": "None",
            "ex:書誌URL": "https://db2.sido.keio.ac.jp/kanseki/bib_detail?bibid=007075_0968",
            "ex:画像URL": "https://db2.sido.keio.ac.jp/kanseki/bib_frame?id=007075-4184&page=2",
            "ex:經典名稱": [
                "阿 (卷)"
            ],
            "ex:資料群名": "宮内庁書陵部蔵宋版大蔵経"
        },
        {
            "@id": "data:T1545_01_005-167.json#底本・校本URL",
            "ex:TEIURL": "None",
            "ex:書誌URL": "https://db2.sido.keio.ac.jp/kanseki/bib_detail?bibid=007075_0968",
            "ex:画像URL": "https://db2.sido.keio.ac.jp/kanseki/bib_frame?id=007075-4185&page=3",
            "ex:經典名稱": [
                "阿 (卷)"
            ],
            "ex:資料群名": "宮内庁書陵部蔵宋版大蔵経"
        },
        {
            "@id": "data:T1545_01_005-168.json#底本・校本URL",
            "ex:TEIURL": "None",
            "ex:書誌URL": "https://db2.sido.keio.ac.jp/kanseki/bib_detail?bibid=007075_0968",
            "ex:画像URL": "https://db2.sido.keio.ac.jp/kanseki/bib_frame?id=007075-4186&page=3",
            "ex:經典名稱": [
                "阿 (卷)"
            ],
            "ex:資料群名": "宮内庁書陵部蔵宋版大蔵経"
        },
        {
            "@id": "data:T1545_01_005-169.json#底本・校本URL",
            "ex:TEIURL": "None",
            "ex:書誌URL": "https://db2.sido.keio.ac.jp/kanseki/bib_detail?bibid=007075_0968",
            "ex:画像URL": "https://db2.sido.keio.ac.jp/kanseki/bib_frame?id=007075-4187&page=3",
            "ex:經典名稱": [
                "阿 (卷)"
            ],
            "ex:資料群名": "宮内庁書陵部蔵宋版大蔵経"
        },
        {
            "@id": "data:T1545_01_005-170.json#底本・校本URL",
            "ex:TEIURL": "None",
            "ex:書誌URL": "https://db2.sido.keio.ac.jp/kanseki/bib_detail?bibid=007075_0968",
            "ex:画像URL": "https://db2.sido.keio.ac.jp/kanseki/bib_frame?id=007075-4188&page=2",
            "ex:經典名稱": [
                "阿 (卷)"
            ],
            "ex:資料群名": "宮内庁書陵部蔵宋版大蔵経"
        },
        {
            "@id": "data:T1545_01_005-171.json#底本・校本URL",
            "ex:TEIURL": "None",
            "ex:書誌URL": "https://db2.sido.keio.ac.jp/kanseki/bib_detail?bibid=007075_0968",
            "ex:画像URL": "https://db2.sido.keio.ac.jp/kanseki/bib_frame?id=007075-4189&page=2",
            "ex:經典名稱": [
                "阿 (卷)"
            ],
            "ex:資料群名": "宮内庁書陵部蔵宋版大蔵経"
        },
        {
            "@id": "data:T1545_01_005-172.json#底本・校本URL",
            "ex:TEIURL": "None",
            "ex:書誌URL": "https://db2.sido.keio.ac.jp/kanseki/bib_detail?bibid=007075_0968",
            "ex:画像URL": "https://db2.sido.keio.ac.jp/kanseki/bib_frame?id=007075-4190&page=2",
            "ex:經典名稱": [
                "阿 (卷)"
            ],
            "ex:資料群名": "宮内庁書陵部蔵宋版大蔵経"
        },
        {
            "@id": "data:T1545_01_005-173.json#底本・校本URL",
            "ex:TEIURL": "None",
            "ex:書誌URL": "https://db2.sido.keio.ac.jp/kanseki/bib_detail?bibid=007075_0968",
            "ex:画像URL": "https://db2.sido.keio.ac.jp/kanseki/bib_frame?id=007075-4191&page=2",
            "ex:經典名稱": [
                "阿 (卷)"
            ],
            "ex:資料群名": "宮内庁書陵部蔵宋版大蔵経"
        },
        {
            "@id": "data:T1545_01_005-174.json#底本・校本URL",
            "ex:TEIURL": "None",
            "ex:書誌URL": "https://db2.sido.keio.ac.jp/kanseki/bib_detail?bibid=007075_0968",
            "ex:画像URL": "https://db2.sido.keio.ac.jp/kanseki/bib_frame?id=007075-4192&page=2",
            "ex:經典名稱": [
                "阿 (卷)"
            ],
            "ex:資料群名": "宮内庁書陵部蔵宋版大蔵経"
        },
        {
            "@id": "data:T1545_01_005-175.json#底本・校本URL",
            "ex:TEIURL": "None",
            "ex:書誌URL": "https://db2.sido.keio.ac.jp/kanseki/bib_detail?bibid=007075_0968",
            "ex:画像URL": "https://db2.sido.keio.ac.jp/kanseki/bib_frame?id=007075-4194&page=2",
            "ex:經典名稱": [
                "阿 (卷)"
            ],
            "ex:資料群名": "宮内庁書陵部蔵宋版大蔵経"
        },
        {
            "@id": "data:T1545_01_005-176.json#底本・校本URL",
            "ex:TEIURL": "None",
            "ex:書誌URL": "https://db2.sido.keio.ac.jp/kanseki/bib_detail?bibid=007075_0968",
            "ex:画像URL": "https://db2.sido.keio.ac.jp/kanseki/bib_frame?id=007075-4195&page=2",
            "ex:經典名稱": [
                "阿 (卷)"
            ],
            "ex:資料群名": "宮内庁書陵部蔵宋版大蔵経"
        },
        {
            "@id": "data:T1545_01_005-177.json#底本・校本URL",
            "ex:TEIURL": "None",
            "ex:書誌URL": "https://db2.sido.keio.ac.jp/kanseki/bib_detail?bibid=007075_0968",
            "ex:画像URL": "https://db2.sido.keio.ac.jp/kanseki/bib_frame?id=007075-4196&page=2",
            "ex:經典名稱": [
                "阿 (卷)"
            ],
            "ex:資料群名": "宮内庁書陵部蔵宋版大蔵経"
        },
        {
            "@id": "data:T1545_01_005-178.json#底本・校本URL",
            "ex:TEIURL": "None",
            "ex:書誌URL": "https://db2.sido.keio.ac.jp/kanseki/bib_detail?bibid=007075_0968",
            "ex:画像URL": "https://db2.sido.keio.ac.jp/kanseki/bib_frame?id=007075-4197&page=2",
            "ex:經典名稱": [
                "阿 (卷)"
            ],
            "ex:資料群名": "宮内庁書陵部蔵宋版大蔵経"
        },
        {
            "@id": "data:T1545_01_005-179.json#底本・校本URL",
            "ex:TEIURL": "None",
            "ex:書誌URL": "https://db2.sido.keio.ac.jp/kanseki/bib_detail?bibid=007075_0968",
            "ex:画像URL": "https://db2.sido.keio.ac.jp/kanseki/bib_frame?id=007075-4198&page=3",
            "ex:經典名稱": [
                "阿 (卷)"
            ],
            "ex:資料群名": "宮内庁書陵部蔵宋版大蔵経"
        },
        {
            "@id": "data:T1545_01_005-180.json#底本・校本URL",
            "ex:TEIURL": "None",
            "ex:書誌URL": "https://db2.sido.keio.ac.jp/kanseki/bib_detail?bibid=007075_0968",
            "ex:画像URL": "https://db2.sido.keio.ac.jp/kanseki/bib_frame?id=007075-4199&page=3",
            "ex:經典名稱": [
                "阿 (卷)"
            ],
            "ex:資料群名": "宮内庁書陵部蔵宋版大蔵経"
        },
        {
            "@id": "data:T1545_01_005-181.json#底本・校本URL",
            "ex:TEIURL": "None",
            "ex:書誌URL": "https://db2.sido.keio.ac.jp/kanseki/bib_detail?bibid=007075_0968",
            "ex:画像URL": "https://db2.sido.keio.ac.jp/kanseki/bib_frame?id=007075-4200&page=3",
            "ex:經典名稱": [
                "阿 (卷)"
            ],
            "ex:資料群名": "宮内庁書陵部蔵宋版大蔵経"
        },
        {
            "@id": "data:T1545_01_005-182.json#底本・校本URL",
            "ex:TEIURL": "None",
            "ex:書誌URL": "https://db2.sido.keio.ac.jp/kanseki/bib_detail?bibid=007075_0968",
            "ex:画像URL": "https://db2.sido.keio.ac.jp/kanseki/bib_frame?id=007075-4201&page=3",
            "ex:經典名稱": [
                "阿 (卷)"
            ],
            "ex:資料群名": "宮内庁書陵部蔵宋版大蔵経"
        },
        {
            "@id": "data:T1545_01_005-183.json#底本・校本URL",
            "ex:TEIURL": "None",
            "ex:書誌URL": "https://db2.sido.keio.ac.jp/kanseki/bib_detail?bibid=007075_0968",
            "ex:画像URL": "https://db2.sido.keio.ac.jp/kanseki/bib_frame?id=007075-4202&page=3",
            "ex:經典名稱": [
                "阿 (卷)"
            ],
            "ex:資料群名": "宮内庁書陵部蔵宋版大蔵経"
        },
        {
            "@id": "data:T1545_01_005-184.json#底本・校本URL",
            "ex:TEIURL": "None",
            "ex:書誌URL": "https://db2.sido.keio.ac.jp/kanseki/bib_detail?bibid=007075_0968",
            "ex:画像URL": "https://db2.sido.keio.ac.jp/kanseki/bib_frame?id=007075-4203&page=3",
            "ex:經典名稱": [
                "阿 (卷)"
            ],
            "ex:資料群名": "宮内庁書陵部蔵宋版大蔵経"
        },
        {
            "@id": "data:T1545_01_005-185.json#底本・校本URL",
            "ex:TEIURL": "None",
            "ex:書誌URL": "https://db2.sido.keio.ac.jp/kanseki/bib_detail?bibid=007075_0968",
            "ex:画像URL": "https://db2.sido.keio.ac.jp/kanseki/bib_frame?id=007075-4205&page=3",
            "ex:經典名稱": [
                "阿 (卷)"
            ],
            "ex:資料群名": "宮内庁書陵部蔵宋版大蔵経"
        },
        {
            "@id": "data:T1545_01_005-186.json#底本・校本URL",
            "ex:TEIURL": "None",
            "ex:書誌URL": "https://db2.sido.keio.ac.jp/kanseki/bib_detail?bibid=007075_0968",
            "ex:画像URL": "https://db2.sido.keio.ac.jp/kanseki/bib_frame?id=007075-4206&page=3",
            "ex:經典名稱": [
                "阿 (卷)"
            ],
            "ex:資料群名": "宮内庁書陵部蔵宋版大蔵経"
        },
        {
            "@id": "data:T1545_01_005-187.json#底本・校本URL",
            "ex:TEIURL": "None",
            "ex:書誌URL": "https://db2.sido.keio.ac.jp/kanseki/bib_detail?bibid=007075_0968",
            "ex:画像URL": "https://db2.sido.keio.ac.jp/kanseki/bib_frame?id=007075-4207&page=2",
            "ex:經典名稱": [
                "阿 (卷)"
            ],
            "ex:資料群名": "宮内庁書陵部蔵宋版大蔵経"
        },
        {
            "@id": "data:T1545_01_005-188.json#底本・校本URL",
            "ex:TEIURL": "None",
            "ex:書誌URL": "https://db2.sido.keio.ac.jp/kanseki/bib_detail?bibid=007075_0968",
            "ex:画像URL": "https://db2.sido.keio.ac.jp/kanseki/bib_frame?id=007075-4208&page=2",
            "ex:經典名稱": [
                "阿 (卷)"
            ],
            "ex:資料群名": "宮内庁書陵部蔵宋版大蔵経"
        },
        {
            "@id": "data:T1545_01_005-189.json#底本・校本URL",
            "ex:TEIURL": "None",
            "ex:書誌URL": "https://db2.sido.keio.ac.jp/kanseki/bib_detail?bibid=007075_0968",
            "ex:画像URL": "https://db2.sido.keio.ac.jp/kanseki/bib_frame?id=007075-4209&page=2",
            "ex:經典名稱": [
                "阿 (卷)"
            ],
            "ex:資料群名": "宮内庁書陵部蔵宋版大蔵経"
        },
        {
            "@id": "data:T1545_01_005-190.json#底本・校本URL",
            "ex:TEIURL": "None",
            "ex:書誌URL": "https://db2.sido.keio.ac.jp/kanseki/bib_detail?bibid=007075_0968",
            "ex:画像URL": "https://db2.sido.keio.ac.jp/kanseki/bib_frame?id=007075-4210&page=2",
            "ex:經典名稱": [
                "阿 (卷)"
            ],
            "ex:資料群名": "宮内庁書陵部蔵宋版大蔵経"
        },
        {
            "@id": "data:T1545_01_005-191.json#底本・校本URL",
            "ex:TEIURL": "None",
            "ex:書誌URL": "https://db2.sido.keio.ac.jp/kanseki/bib_detail?bibid=007075_0968",
            "ex:画像URL": "https://db2.sido.keio.ac.jp/kanseki/bib_frame?id=007075-4211&page=2",
            "ex:經典名稱": [
                "阿 (卷)"
            ],
            "ex:資料群名": "宮内庁書陵部蔵宋版大蔵経"
        },
        {
            "@id": "data:T1545_01_005-192.json#底本・校本URL",
            "ex:TEIURL": "None",
            "ex:書誌URL": "https://db2.sido.keio.ac.jp/kanseki/bib_detail?bibid=007075_0968",
            "ex:画像URL": "https://db2.sido.keio.ac.jp/kanseki/bib_frame?id=007075-4212&page=3",
            "ex:經典名稱": [
                "阿 (卷)"
            ],
            "ex:資料群名": "宮内庁書陵部蔵宋版大蔵経"
        },
        {
            "@id": "data:T1545_01_005-193.json#底本・校本URL",
            "ex:TEIURL": "None",
            "ex:書誌URL": "https://db2.sido.keio.ac.jp/kanseki/bib_detail?bibid=007075_0968",
            "ex:画像URL": "https://db2.sido.keio.ac.jp/kanseki/bib_frame?id=007075-4213&page=2",
            "ex:經典名稱": [
                "阿 (卷)"
            ],
            "ex:資料群名": "宮内庁書陵部蔵宋版大蔵経"
        },
        {
            "@id": "data:T1545_01_005-194.json#底本・校本URL",
            "ex:TEIURL": "None",
            "ex:書誌URL": "https://db2.sido.keio.ac.jp/kanseki/bib_detail?bibid=007075_0968",
            "ex:画像URL": "https://db2.sido.keio.ac.jp/kanseki/bib_frame?id=007075-4214&page=3",
            "ex:經典名稱": [
                "阿 (卷)"
            ],
            "ex:資料群名": "宮内庁書陵部蔵宋版大蔵経"
        }
    ],
    "ex:脚注": [
        {
            "@id": "data:T1545_01_005.json#脚注",
            "ex:texts": [
                {
                    "@id": "data:T1545_01_005-1.json#テキスト",
                    "ex:刊写形態": "刊",
                    "ex:刊写者": "None",
                    "ex:国": "中国",
                    "ex:巻": "None",
                    "ex:年": "1104",
                    "ex:底本推定": "None",
                    "ex:時代": "宋",
                    "ex:標準名称": "宮本",
                    "ex:略号の使用": "専号使用",
                    "ex:略号解説": "〈宮〉宮内省圖書寮本（舊宋本）（The Old Sung Edition〔A. D. 1104-1148〕belonging to the Library of the Imperial Household）",
                    "ex:関与形態": "None",
                    "ex:関与者": "None",
                    "ex:～年": "1148"
                }
            ],
            "ex:テキスト": "〈宮〉",
            "ex:備考": "None",
            "ex:底本/校本": "校本",
            "ex:所蔵者": [
                {
                    "@id": "data:T1545_01_005-1.json#所蔵者",
                    "ex:国": "日本",
                    "ex:所蔵者": "宮内庁書陵部"
                }
            ],
            "ex:新添": "None"
        }
    ],
    "ex:酉目": [],
    "ex:酉蓮社本IIIコレクション": []
}