{
    "@context": "https://static.toyobunko-lab.jp/taishozo/context.json",
    "@id": "data:T1613_01_004.json",
    "data": {
        "id": "T1613_01_004",
        "relationships": {
            "基本情報 + SAT頭出し用 + 勘同目録IIIFコレクション": {
                "data": {
                    "ID": "T1613_01",
                    "SAT頭出し用：ページ": 850,
                    "SAT頭出し用：枝番+ABC": null,
                    "SAT頭出し用：段": "c",
                    "SAT頭出し用：画像URL": "https://dzkimgs.l.u-tokyo.ac.jp/yurenja_kkz/?manifest=https://dzkimgs.l.u-tokyo.ac.jp/iiif/taisho/manifests/1613_31_manifest.json&canvas=https://dzkimgs.l.u-tokyo.ac.jp/iiif/taisho/manifests/canvas/31_0850.json",
                    "SAT頭出し用：経典番号-ABC": "T1613",
                    "SAT頭出し用：行": 11,
                    "SAT頭出し用：開始巻": 31,
                    "佛經目錄規範資料庫：作訳者1": "安慧",
                    "佛經目錄規範資料庫：作訳者2": "地婆訶羅",
                    "佛經目錄規範資料庫：作訳者3": null,
                    "佛經目錄規範資料庫：作訳者URL1": "A000371",
                    "佛經目錄規範資料庫：作訳者URL2": "A000332",
                    "佛經目錄規範資料庫：作訳者URL3": null,
                    "佛經目錄規範資料庫：規範碼": "CA0001293",
                    "勘同目録IIIFコレクション：kmID": "km1644",
                    "勘同目録IIIFコレクション：toページ": 435,
                    "勘同目録IIIFコレクション：to段": "b",
                    "勘同目録IIIFコレクション：ページ": 435,
                    "勘同目録IIIFコレクション：段": "b",
                    "勘同目録：❶名称〔巴〕": null,
                    "勘同目録：❶名称〔支〕": "Ta-tch'eng-kouang-wou-yun-louen",
                    "勘同目録：❶名称〔日〕": "Dai-jō-kwō-go-un-ron",
                    "勘同目録：❶名称〔梵〕": "Pañcaskandhaprakaraṇavaibhāṣya",
                    "勘同目録：❶名称〔西藏名〕": null,
                    "勘同目録：❶名称：異名略名": "廣五蘊論,大乘五蘊論",
                    "勘同目録：❷著訳者名、著訳年代": "唐（垂拱元 A.D. 685） 地婆訶羅譯",
                    "勘同目録：❸Nj": 1175,
                    "勘同目録：❸元": "盡",
                    "勘同目録：❸卍": "二十一．二",
                    "勘同目録：❸宋": "盡",
                    "勘同目録：❸明": "投",
                    "勘同目録：❸縮": "往十",
                    "勘同目録：❸麗": "則",
                    "勘同目録：巻数": 1,
                    "勘同目録：巻数注記": null,
                    "勘同目録：書名": "大乘廣五蘊論",
                    "基本情報：出版年月日": 19251215,
                    "基本情報：収録巻次": 31,
                    "基本情報：巻数": 1,
                    "基本情報：枝番": 1,
                    "基本情報：経典別名": "廣五蘊論,大乘五蘊論",
                    "基本情報：経典名": "大乘廣五蘊論",
                    "基本情報：経典番号": "T1613",
                    "基本情報：訳著者": "安慧菩薩造　唐地婆訶羅譯",
                    "基本情報：訳著者1-4": "安慧菩薩|地婆訶羅",
                    "基本情報：部門": "瑜伽部下",
                    "基本情報：配本": 20
                }
            }
        },
        "type": "item"
    },
    "ex:sat": [
        {
            "@id": "data:T1613_01_004.json#SAT頭出し用",
            "ex:url": "https://21dzk.l.u-tokyo.ac.jp/SAT2018/T1613_01_.31.0850c11.html"
        }
    ],
    "ex:勘同目録": [
        {
            "@id": "data:T1613_01_004.json#勘同目録",
            "ex:texts": [
                {
                    "@id": "data:T1613_01_004-1.json#テキスト",
                    "ex:刊写形態": "刊",
                    "ex:刊写者": "None",
                    "ex:国": "中国",
                    "ex:巻": "None",
                    "ex:年": "1601",
                    "ex:時代": "明",
                    "ex:標準名称": "明本",
                    "ex:関与形態": "None",
                    "ex:関与者": "None"
                }
            ],
            "ex:❹": "明本",
            "ex:❼": "None",
            "ex:❼備考": "None",
            "ex:底本/校本": "校本",
            "ex:所蔵者": []
        }
    ],
    "ex:勘同目録IIIFコレクション": [
        {
            "@id": "data:T1613_01.json#勘同目録IIIFコレクション",
            "ex:kmID": "km1644",
            "ex:pos": [
                283
            ],
            "ex:toページ": "435",
            "ex:to段": "b",
            "ex:url": [
                "https://static.toyobunko-lab.jp/taishozo/api/iiif/kandomokuroku/manifest.json"
            ],
            "ex:ページ": "435",
            "ex:段": "b"
        }
    ],
    "ex:基本情報": [
        {
            "@id": "data:T1613_01_004.json#基本情報",
            "ex:No.": "T1613_01_004",
            "ex:経典": [
                {
                    "@id": "keiten:T1613_01.json",
                    "ex:出版年月日": "19251215",
                    "ex:収録巻次": "31",
                    "ex:巻数": "1",
                    "ex:枝番": "1",
                    "ex:経典別名": "廣五蘊論,大乘五蘊論",
                    "ex:経典名": "大乘廣五蘊論",
                    "ex:経典番号": "T1613",
                    "ex:訳著者": "安慧菩薩造　唐地婆訶羅譯",
                    "ex:訳著者1-4": "安慧菩薩|地婆訶羅",
                    "ex:部門": "瑜伽部下",
                    "ex:配本": "20"
                }
            ]
        }
    ],
    "ex:底本校本URL": [],
    "ex:脚注": [
        {
            "@id": "data:T1613_01_004.json#脚注",
            "ex:texts": [
                {
                    "@id": "data:T1613_01_004-1.json#テキスト",
                    "ex:刊写形態": "刊",
                    "ex:刊写者": "None",
                    "ex:国": "中国",
                    "ex:巻": "None",
                    "ex:年": "1601",
                    "ex:底本推定": "None",
                    "ex:時代": "明",
                    "ex:標準名称": "明本",
                    "ex:略号の使用": "専号使用",
                    "ex:略号解説": "〈明〉明本（The ‘Ming Edition’ A. D. 1601）",
                    "ex:関与形態": "None",
                    "ex:関与者": "None",
                    "ex:～年": "None"
                }
            ],
            "ex:テキスト": "〈明〉",
            "ex:備考": "None",
            "ex:底本/校本": "校本",
            "ex:所蔵者": [],
            "ex:新添": "None"
        }
    ],
    "ex:酉目": [
        {
            "@id": "data:T1613_01_004-1.json#酉目",
            "ex:to枝番": "2",
            "ex:url": [
                "https://static.toyobunko-lab.jp/u-renja/search/?main[refinementList][通番]=1180"
            ],
            "ex:枝番": "1",
            "ex:經典番號": "U1169",
            "ex:通番": "1180"
        }
    ],
    "ex:酉蓮社本IIIコレクション": []
}