{
    "@context": "https://static.toyobunko-lab.jp/taishozo/context.json",
    "@id": "data:T1760_01_002.json",
    "data": {
        "id": "T1760_01_002",
        "relationships": {
            "基本情報 + SAT頭出し用 + 勘同目録IIIFコレクション": {
                "data": {
                    "ID": "T1760_01",
                    "SAT頭出し用：ページ": 350,
                    "SAT頭出し用：枝番+ABC": null,
                    "SAT頭出し用：段": "c",
                    "SAT頭出し用：画像URL": "https://dzkimgs.l.u-tokyo.ac.jp/yurenja_kkz/?manifest=https://dzkimgs.l.u-tokyo.ac.jp/iiif/taisho/manifests/1760_37_manifest.json&canvas=https://dzkimgs.l.u-tokyo.ac.jp/iiif/taisho/manifests/canvas/37_0350.json",
                    "SAT頭出し用：経典番号-ABC": "T1760",
                    "SAT頭出し用：行": 1,
                    "SAT頭出し用：開始巻": 37,
                    "佛經目錄規範資料庫：作訳者1": "智圓",
                    "佛經目錄規範資料庫：作訳者2": null,
                    "佛經目錄規範資料庫：作訳者3": null,
                    "佛經目錄規範資料庫：作訳者URL1": "A001282",
                    "佛經目錄規範資料庫：作訳者URL2": null,
                    "佛經目錄規範資料庫：作訳者URL3": null,
                    "佛經目錄規範資料庫：規範碼": "CA0000034",
                    "勘同目録IIIFコレクション：kmID": "km1792",
                    "勘同目録IIIFコレクション：toページ": 460,
                    "勘同目録IIIFコレクション：to段": "c",
                    "勘同目録IIIFコレクション：ページ": 460,
                    "勘同目録IIIFコレクション：段": "b",
                    "勘同目録：❶名称〔巴〕": null,
                    "勘同目録：❶名称〔支〕": "Fo-chouo-a-mi-t'o-king-chou",
                    "勘同目録：❶名称〔日〕": "Bus-setsu-a-mi-da-kyō-sho",
                    "勘同目録：❶名称〔梵〕": null,
                    "勘同目録：❶名称〔西藏名〕": null,
                    "勘同目録：❶名称：異名略名": null,
                    "勘同目録：❷著訳者名、著訳年代": "宋（開寶九－乾興元 A.D. 976-1022） 智圓述",
                    "勘同目録：❸Nj": null,
                    "勘同目録：❸元": null,
                    "勘同目録：❸卍": "續一．三十三．二",
                    "勘同目録：❸宋": null,
                    "勘同目録：❸明": null,
                    "勘同目録：❸縮": null,
                    "勘同目録：❸麗": null,
                    "勘同目録：巻数": 1,
                    "勘同目録：巻数注記": null,
                    "勘同目録：書名": "佛説阿彌陀經疏",
                    "基本情報：出版年月日": 19261015,
                    "基本情報：収録巻次": 37,
                    "基本情報：巻数": 1,
                    "基本情報：枝番": 1,
                    "基本情報：経典別名": "阿彌陀經疏,阿彌陀經義疏",
                    "基本情報：経典名": "佛説阿彌陀經疏",
                    "基本情報：経典番号": "T1760",
                    "基本情報：訳著者": "宋釋智圓述",
                    "基本情報：訳著者1-4": "釋智圓",
                    "基本情報：部門": "経疏部5",
                    "基本情報：配本": 30
                }
            }
        },
        "type": "item"
    },
    "ex:sat": [
        {
            "@id": "data:T1760_01_002.json#SAT頭出し用",
            "ex:url": "https://21dzk.l.u-tokyo.ac.jp/SAT2018/T1760_01_.37.0350c01.html"
        }
    ],
    "ex:勘同目録": [
        {
            "@id": "data:T1760_01_002.json#勘同目録",
            "ex:texts": [],
            "ex:❹": "校本無",
            "ex:❼": "None",
            "ex:❼備考": "None",
            "ex:底本/校本": "None",
            "ex:所蔵者": []
        }
    ],
    "ex:勘同目録IIIFコレクション": [
        {
            "@id": "data:T1760_01.json#勘同目録IIIFコレクション",
            "ex:kmID": "km1792",
            "ex:pos": [
                308
            ],
            "ex:toページ": "460",
            "ex:to段": "c",
            "ex:url": [
                "https://static.toyobunko-lab.jp/taishozo/api/iiif/kandomokuroku/manifest.json"
            ],
            "ex:ページ": "460",
            "ex:段": "b"
        }
    ],
    "ex:基本情報": [
        {
            "@id": "data:T1760_01_002.json#基本情報",
            "ex:No.": "T1760_01_002",
            "ex:経典": [
                {
                    "@id": "keiten:T1760_01.json",
                    "ex:出版年月日": "19261015",
                    "ex:収録巻次": "37",
                    "ex:巻数": "1",
                    "ex:枝番": "1",
                    "ex:経典別名": "阿彌陀經疏,阿彌陀經義疏",
                    "ex:経典名": "佛説阿彌陀經疏",
                    "ex:経典番号": "T1760",
                    "ex:訳著者": "宋釋智圓述",
                    "ex:訳著者1-4": "釋智圓",
                    "ex:部門": "経疏部5",
                    "ex:配本": "30"
                }
            ]
        }
    ],
    "ex:底本校本URL": [],
    "ex:脚注": [
        {
            "@id": "data:T1760_01_002.json#脚注",
            "ex:texts": [],
            "ex:テキスト": "None",
            "ex:備考": "None",
            "ex:底本/校本": "None",
            "ex:所蔵者": [],
            "ex:新添": "None"
        }
    ],
    "ex:酉目": [],
    "ex:酉蓮社本IIIコレクション": []
}