{
    "@context": "https://static.toyobunko-lab.jp/taishozo/context.json",
    "@id": "data:T1785-002.json",
    "ex:sat": [
        {
            "@id": "data:T1785-002.json#SAT頭出し用",
            "ex:url": "https://21dzk.l.u-tokyo.ac.jp/SAT2018/T1785_.39.0046b21.html"
        }
    ],
    "ex:勘同目録": [
        {
            "@id": "data:T1785-002.json#勘同目録",
            "ex:texts": [
                {
                    "@id": "data:T1785-002-1.json#テキスト",
                    "ex:刊写形態": [
                        "写"
                    ],
                    "ex:国": [
                        "日本"
                    ],
                    "ex:年": [
                        "1292"
                    ],
                    "ex:時代": [
                        "鎌倉"
                    ],
                    "ex:標準名称": [
                        "寶菩提院藏本"
                    ]
                }
            ],
            "ex:❹": [
                "寶菩提院本"
            ],
            "ex:❼": [
                "正應五年寫"
            ],
            "ex:❼備考": [],
            "ex:底本/校本": [
                "校本"
            ],
            "ex:所蔵者": [
                {
                    "@id": "data:T1785-002-1.json#所蔵者",
                    "ex:国": [
                        "日本"
                    ],
                    "ex:所蔵者": [
                        "寶菩提院"
                    ]
                }
            ]
        }
    ],
    "ex:勘同目録IIIFコレクション": [
        {
            "@id": "data:T1785.json#勘同目録IIIFコレクション",
            "ex:kmID": [
                "km1817"
            ],
            "ex:pos": [
                312
            ],
            "ex:toページ": [
                464
            ],
            "ex:to段": [
                "c"
            ],
            "ex:url": [
                "https://static.toyobunko-lab.jp/taishozo/api/iiif/kandomokuroku/manifest.json"
            ],
            "ex:ページ": [
                464
            ],
            "ex:段": [
                "b"
            ]
        }
    ],
    "ex:基本情報": [
        {
            "@id": "data:T1785-002.json#基本情報",
            "ex:No.": "T1785-002",
            "ex:経典": [
                {
                    "@id": "keiten:T1785.json",
                    "ex:出版年月日": [
                        19270215
                    ],
                    "ex:収録巻次": [
                        39
                    ],
                    "ex:巻数": [
                        6
                    ],
                    "ex:枝番": [
                        1
                    ],
                    "ex:経典別名": [
                        "金光明文句,光明文句,金光明經疏,金光明疏"
                    ],
                    "ex:経典名": [
                        "金光明經文句"
                    ],
                    "ex:経典番号": [
                        "T1785"
                    ],
                    "ex:訳著者": [
                        "隋釋智顗説　唐釋灌頂録"
                    ],
                    "ex:訳著者1-4": [
                        "釋智顗",
                        "釋灌頂"
                    ],
                    "ex:部門": [
                        "経疏部7"
                    ],
                    "ex:配本": [
                        34
                    ]
                }
            ]
        }
    ],
    "ex:底本校本URL": [],
    "ex:脚注": [
        {
            "@id": "data:T1785-002.json#脚注",
            "ex:texts": [
                {
                    "@id": "data:T1785-002-1.json#テキスト",
                    "ex:刊写形態": [
                        "写"
                    ],
                    "ex:刊写者": [],
                    "ex:国": [
                        "日本"
                    ],
                    "ex:巻": [],
                    "ex:年": [
                        "1292"
                    ],
                    "ex:底本推定": [],
                    "ex:時代": [
                        "鎌倉"
                    ],
                    "ex:標準名称": [
                        "寶菩提院藏本"
                    ],
                    "ex:略号の使用": [],
                    "ex:略号解説": [],
                    "ex:関与形態": [],
                    "ex:関与者": [],
                    "ex:～年": []
                }
            ],
            "ex:テキスト": [
                "正應五年寫寶菩提院藏本"
            ],
            "ex:備考": [],
            "ex:底本/校本": [
                "校本"
            ],
            "ex:所蔵者": [
                {
                    "@id": "data:T1785-002-1.json#所蔵者",
                    "ex:国": [
                        "日本"
                    ],
                    "ex:所蔵者": [
                        "寶菩提院"
                    ]
                }
            ],
            "ex:新添": [
                "〈甲〉"
            ]
        }
    ],
    "ex:酉目": [],
    "ex:酉蓮社本IIIコレクション": []
}