{
    "@context": "https://static.toyobunko-lab.jp/taishozo/context.json",
    "@id": "data:T1912-001.json",
    "ex:sat": [
        {
            "@id": "data:T1912-001.json#SAT頭出し用",
            "ex:url": "https://21dzk.l.u-tokyo.ac.jp/SAT2018/T1912_.46.0141a01.html"
        }
    ],
    "ex:勘同目録": [
        {
            "@id": "data:T1912-001.json#勘同目録",
            "ex:texts": [
                {
                    "@id": "data:T1912-001-1.json#テキスト",
                    "ex:刊写形態": [
                        "刊"
                    ],
                    "ex:国": [
                        "中国"
                    ],
                    "ex:年": [
                        "1639"
                    ],
                    "ex:時代": [
                        "明"
                    ],
                    "ex:標準名称": [
                        "增上寺報恩藏藏本"
                    ]
                }
            ],
            "ex:❹": [
                "增上寺報恩藏本"
            ],
            "ex:❼": [
                "崇禎十二年刊"
            ],
            "ex:❼備考": [],
            "ex:底本/校本": [
                "底本"
            ],
            "ex:所蔵者": [
                {
                    "@id": "data:T1912-001-1.json#所蔵者",
                    "ex:国": [
                        "日本"
                    ],
                    "ex:所蔵者": [
                        "增上寺報恩藏"
                    ]
                }
            ]
        }
    ],
    "ex:勘同目録IIIFコレクション": [
        {
            "@id": "data:T1912.json#勘同目録IIIFコレクション",
            "ex:kmID": [
                "km1945"
            ],
            "ex:toページ": [
                492
            ],
            "ex:to段": [
                "a"
            ],
            "ex:url": "http://codh.rois.ac.jp/software/iiif-curation-viewer/demo/?manifest=https://static.toyobunko-lab.jp/taishozo/iiif/kandomokuroku/manifest.json&pos=$XXX",
            "ex:ページ": [
                492
            ],
            "ex:段": [
                "a"
            ]
        }
    ],
    "ex:基本情報": [
        {
            "@id": "data:T1912-001.json#基本情報",
            "ex:No.": "T1912-001",
            "ex:経典": [
                {
                    "@id": "keiten:T1912.json",
                    "ex:出版年月日": [
                        19271215
                    ],
                    "ex:収録巻次": [
                        46
                    ],
                    "ex:巻数": [
                        10
                    ],
                    "ex:枝番": [
                        1
                    ],
                    "ex:経典別名": [
                        "摩訶止觀輔行傳弘決,止觀輔行,止觀記"
                    ],
                    "ex:経典名": [
                        "止觀輔行傳弘決"
                    ],
                    "ex:経典番号": [
                        "T1912"
                    ],
                    "ex:訳著者": [
                        "唐釋湛然述"
                    ],
                    "ex:訳著者1-4": [
                        "釋湛然"
                    ],
                    "ex:部門": [
                        "諸宗部3"
                    ],
                    "ex:配本": [
                        44
                    ]
                }
            ]
        }
    ],
    "ex:底本校本URL": [],
    "ex:脚注": [
        {
            "@id": "data:T1912-001.json#脚注",
            "ex:texts": [
                {
                    "@id": "data:T1912-001-1.json#テキスト",
                    "ex:刊写形態": [
                        "刊"
                    ],
                    "ex:刊写者": [],
                    "ex:国": [
                        "中国"
                    ],
                    "ex:巻": [],
                    "ex:年": [
                        "1639"
                    ],
                    "ex:底本推定": [],
                    "ex:時代": [
                        "明"
                    ],
                    "ex:標準名称": [
                        "增上寺報恩藏藏本"
                    ],
                    "ex:略号の使用": [],
                    "ex:略号解説": [],
                    "ex:関与形態": [],
                    "ex:関与者": [],
                    "ex:～年": []
                }
            ],
            "ex:テキスト": [
                "崇禎十二年刊增上寺報恩藏本"
            ],
            "ex:備考": [],
            "ex:底本/校本": [
                "底本"
            ],
            "ex:所蔵者": [
                {
                    "@id": "data:T1912-001-1.json#所蔵者",
                    "ex:国": [
                        "日本"
                    ],
                    "ex:所蔵者": [
                        "增上寺報恩藏"
                    ]
                }
            ],
            "ex:新添": [
                "〈原〉"
            ]
        }
    ],
    "ex:酉目": [
        {
            "@id": "data:T1912-001-1.json#酉目",
            "ex:to枝番": [
                41
            ],
            "ex:url": "https://static.toyobunko-lab.jp/u-renja/search/?main[refinementList][通番]=1361",
            "ex:枝番": [
                1
            ],
            "ex:經典番號": [
                "U1532"
            ],
            "ex:通番": [
                1549
            ]
        }
    ],
    "ex:酉蓮社本IIIコレクション": [
        {
            "@id": "data:T1912-001-1.json#酉蓮社本IIIFコレクション",
            "ex:from": [
                1
            ],
            "ex:to": [
                1118
            ],
            "ex:url": "http://codh.rois.ac.jp/software/iiif-curation-viewer/demo/?manifest=https://static.toyobunko-lab.jp/u-renja/iiif2/XXX/manifest.json",
            "ex:画像フォルダ": [
                "u-renja1549"
            ],
            "ex:経典名": [
                "止觀輔行傳弘決10卷"
            ]
        }
    ]
}