{
    "@context": "https://static.toyobunko-lab.jp/taishozo/context.json",
    "@id": "data:T2163_01_001.json",
    "data": {
        "id": "T2163_01_001",
        "relationships": {
            "基本情報 + SAT頭出し用 + 勘同目録IIIFコレクション": {
                "data": {
                    "ID": "T2163_01",
                    "SAT頭出し用：ページ": 1068,
                    "SAT頭出し用：枝番+ABC": null,
                    "SAT頭出し用：段": "c",
                    "SAT頭出し用：画像URL": "https://dzkimgs.l.u-tokyo.ac.jp/yurenja_kkz/?manifest=https://dzkimgs.l.u-tokyo.ac.jp/iiif/taisho/manifests/2163_55_manifest.json&canvas=https://dzkimgs.l.u-tokyo.ac.jp/iiif/taisho/manifests/canvas/55_1068.json",
                    "SAT頭出し用：経典番号-ABC": "T2163",
                    "SAT頭出し用：行": 3,
                    "SAT頭出し用：開始巻": 55,
                    "佛經目錄規範資料庫：作訳者1": "常曉",
                    "佛經目錄規範資料庫：作訳者2": null,
                    "佛經目錄規範資料庫：作訳者3": null,
                    "佛經目錄規範資料庫：作訳者URL1": "A001042",
                    "佛經目錄規範資料庫：作訳者URL2": null,
                    "佛經目錄規範資料庫：作訳者URL3": null,
                    "佛經目錄規範資料庫：規範碼": "CA0000437",
                    "勘同目録IIIFコレクション：kmID": "km2206",
                    "勘同目録IIIFコレクション：toページ": 654,
                    "勘同目録IIIFコレクション：to段": "b",
                    "勘同目録IIIFコレクション：ページ": 654,
                    "勘同目録IIIFコレクション：段": "b",
                    "勘同目録：❶名称〔巴〕": null,
                    "勘同目録：❶名称〔支〕": "Tch'ang-hiao-ho-chang-ts'ing-lai-mou-lou",
                    "勘同目録：❶名称〔日〕": "Jō-gyō-wa-jō-shō-rai-moku-roku-",
                    "勘同目録：❶名称〔梵〕": null,
                    "勘同目録：❶名称〔西藏名〕": null,
                    "勘同目録：❶名称：異名略名": null,
                    "勘同目録：❷著訳者名、著訳年代": "日本（承和六 A.D. 839） 常曉撰",
                    "勘同目録：❸Nj": null,
                    "勘同目録：❸元": null,
                    "勘同目録：❸卍": null,
                    "勘同目録：❸宋": null,
                    "勘同目録：❸明": null,
                    "勘同目録：❸縮": null,
                    "勘同目録：❸麗": null,
                    "勘同目録：巻数": 1,
                    "勘同目録：巻数注記": null,
                    "勘同目録：書名": "常曉和尚請來目録",
                    "基本情報：出版年月日": 19281115,
                    "基本情報：収録巻次": 55,
                    "基本情報：巻数": 1,
                    "基本情報：枝番": 1,
                    "基本情報：経典別名": "請來録,常曉請來録",
                    "基本情報：経典名": "常曉和尚請來目録",
                    "基本情報：経典番号": "T2163",
                    "基本情報：訳著者": "日本釋常曉撰",
                    "基本情報：訳著者1-4": "釋常曉",
                    "基本情報：部門": "目録部全",
                    "基本情報：配本": 55
                }
            }
        },
        "type": "item"
    },
    "ex:sat": [
        {
            "@id": "data:T2163_01_001.json#SAT頭出し用",
            "ex:url": "https://21dzk.l.u-tokyo.ac.jp/SAT2018/T2163_01_.55.1068c03.html"
        }
    ],
    "ex:勘同目録": [
        {
            "@id": "data:T2163_01_001.json#勘同目録",
            "ex:texts": [
                {
                    "@id": "data:T2163_01_001-1.json#テキスト",
                    "ex:刊写形態": "写",
                    "ex:刊写者": "None",
                    "ex:国": "日本",
                    "ex:巻": "None",
                    "ex:年": "1185",
                    "ex:時代": "鎌倉",
                    "ex:標準名称": "高山寺藏本",
                    "ex:関与形態": "None",
                    "ex:関与者": "None"
                }
            ],
            "ex:❹": "高山寺本",
            "ex:❼": "鎌倉時代寫",
            "ex:❼備考": "None",
            "ex:底本/校本": "底本",
            "ex:所蔵者": [
                {
                    "@id": "data:T2163_01_001-1.json#所蔵者",
                    "ex:国": "日本",
                    "ex:所蔵者": "高山寺"
                }
            ]
        }
    ],
    "ex:勘同目録IIIFコレクション": [
        {
            "@id": "data:T2163_01.json#勘同目録IIIFコレクション",
            "ex:kmID": "km2206",
            "ex:pos": [
                502
            ],
            "ex:toページ": "654",
            "ex:to段": "b",
            "ex:url": [
                "https://static.toyobunko-lab.jp/taishozo/api/iiif/kandomokuroku/manifest.json"
            ],
            "ex:ページ": "654",
            "ex:段": "b"
        }
    ],
    "ex:基本情報": [
        {
            "@id": "data:T2163_01_001.json#基本情報",
            "ex:No.": "T2163_01_001",
            "ex:経典": [
                {
                    "@id": "keiten:T2163_01.json",
                    "ex:出版年月日": "19281115",
                    "ex:収録巻次": "55",
                    "ex:巻数": "1",
                    "ex:枝番": "1",
                    "ex:経典別名": "請來録,常曉請來録",
                    "ex:経典名": "常曉和尚請來目録",
                    "ex:経典番号": "T2163",
                    "ex:訳著者": "日本釋常曉撰",
                    "ex:訳著者1-4": "釋常曉",
                    "ex:部門": "目録部全",
                    "ex:配本": "55"
                }
            ]
        }
    ],
    "ex:底本校本URL": [],
    "ex:脚注": [
        {
            "@id": "data:T2163_01_001.json#脚注",
            "ex:texts": [
                {
                    "@id": "data:T2163_01_001-1.json#テキスト",
                    "ex:刊写形態": "写",
                    "ex:刊写者": "None",
                    "ex:国": "日本",
                    "ex:巻": "None",
                    "ex:年": "1185",
                    "ex:底本推定": "None",
                    "ex:時代": "鎌倉",
                    "ex:標準名称": "高山寺藏本",
                    "ex:略号の使用": "None",
                    "ex:略号解説": "None",
                    "ex:関与形態": "None",
                    "ex:関与者": "None",
                    "ex:～年": "1333"
                }
            ],
            "ex:テキスト": "鎌倉時代寫高山寺藏本",
            "ex:備考": "None",
            "ex:底本/校本": "底本",
            "ex:所蔵者": [
                {
                    "@id": "data:T2163_01_001-1.json#所蔵者",
                    "ex:国": "日本",
                    "ex:所蔵者": "高山寺"
                }
            ],
            "ex:新添": "〈原〉"
        }
    ],
    "ex:酉目": [],
    "ex:酉蓮社本IIIコレクション": []
}