{
    "@context": "https://taishozo.github.io/db/context.json",
    "@id": "data:01229.json",
    "ex:sat": [
        {
            "@id": "data:01229.json#SAT頭出し用",
            "ex:url": "https://21dzk.l.u-tokyo.ac.jp/SAT2018/T0276_.09.0383b13.html"
        }
    ],
    "ex:勘同目録": [
        {
            "@id": "data:01229.json#勘同目録",
            "ex:texts": [
                {
                    "@id": "data:01229.json#テキスト1（勘同目録）",
                    "ex:刊写形態": "写",
                    "ex:国": "日本",
                    "ex:年": "806",
                    "ex:時代": "平安",
                    "ex:標準名称": "仁和寺藏本",
                    "ex:～年": "1185"
                }
            ],
            "ex:❹": "仁和寺本",
            "ex:❼": "仁和寺本、平安時代寫",
            "ex:底本/校本": "校本",
            "ex:所蔵者": [
                {
                    "@id": "data:01229.json#所蔵者1（勘同目録）",
                    "ex:国": "日本",
                    "ex:所蔵者": "仁和寺"
                }
            ]
        }
    ],
    "ex:勘同目録IIIFコレクション": [
        {
            "@id": "data:01229.json#勘同目録IIIFコレクション",
            "ex:kmID": "km0277",
            "ex:toページ": 225,
            "ex:to段": "b",
            "ex:url": "http://codh.rois.ac.jp/software/iiif-curation-viewer/demo/?manifest=https://taishozo.github.io/db/iiif/kandomokuroku/manifest.json&pos=73",
            "ex:ページ": "225",
            "ex:段": "b"
        }
    ],
    "ex:基本情報": [
        {
            "@id": "data:01229.json#基本情報",
            "ex:No.": "01229",
            "ex:経典": [
                {
                    "@id": "keiten:T0276.json",
                    "ex:出版年月日": [
                        "1925-07-15"
                    ],
                    "ex:収録巻次": 9,
                    "ex:枝番": 1,
                    "ex:経典名": "無量義經",
                    "ex:経典番号": "T0276",
                    "ex:部門": "法華部全/華厳部上",
                    "ex:配本": [
                        15
                    ]
                }
            ]
        }
    ],
    "ex:脚注": [
        {
            "@id": "data:01229.json#脚注",
            "ex:texts": [],
            "ex:所蔵者": []
        }
    ],
    "ex:酉目": [],
    "ex:酉蓮社本IIIコレクション": []
}